{"c2dictionary":true,"data":{"bullet":"{\"table\":{\"name\":{\"0\":\"红蝠-X\",\"1\":\"寒冰-M\",\"2\":\"蓝光-D\",\"3\":\"疾风-W\",\"4\":\"紫塔激光炮\",\"5\":\"红石激光炮\",\"6\":\"钢铁扩散器\",\"7\":\"钢铁散射器\",\"8\":\"热焰号\",\"9\":\"时光号\",\"10\":\"能量号\",\"11\":\"傀儡\",\"12\":\"光球\",\"13\":\"食人花\",\"14\":\"红钢\",\"15\":\"海神\",\"16\":\"恶梦\",\"17\":\"神龙\",\"18\":\"审判者\",\"19\":\"亚瑟\",\"20\":\"噪音\",\"21\":\"食人花2号\",\"22\":\"红钢2号\",\"23\":\"海神2号\",\"24\":\"黄蜂号\",\"25\":\"红蜘蛛\",\"26\":\"绿甲虫\",\"27\":\"幽灵蜘蛛\",\"28\":\"恶梦2号\",\"29\":\"神龙2号\",\"30\":\"审判者2号\",\"31\":\"亚瑟2号\",\"32\":\"噪音2号\",\"33\":\"食人花3号\",\"34\":\"红钢3号\",\"35\":\"海神3号\",\"36\":\"恶梦3号\",\"37\":\"神龙3号\",\"38\":\"审判者3号\",\"39\":\"亚瑟3号\",\"40\":\"噪音3号\",\"41\":\"天使护卫\",\"42\":\"超音战士\",\"43\":\"黑暗骑士\",\"44\":\"霹雳巨钳\",\"45\":\"烈火凤凰\",\"46\":\"小火箭\",\"47\":\"大火箭\",\"48\":\"敌人子弹\",\"49\":\"紫色量产\",\"50\":\"红色量产\",\"51\":\"蓝色量产\",\"52\":\"突刺探测机\",\"53\":\"旋转刺刃\",\"54\":\"游荡幽灵\",\"55\":\"绿色装甲\",\"56\":\"蓝色装甲\",\"57\":\"装载机\",\"58\":\"瑟雷夫\",\"59\":\"幻影魔晶\",\"60\":\"紫色水晶\",\"61\":\"量子蓝\",\"62\":\"量子绿\",\"63\":\"裁决者\",\"64\":\"感染者\",\"65\":\"月面狂袭\",\"66\":\"银河护卫\",\"67\":\"蜂刺\",\"68\":\"精英初代\",\"69\":\"精英鲨鱼\",\"70\":\"精英凤凰\",\"71\":\"精英黄蜂\",\"72\":\"精英藤蔓\",\"73\":\"精英混沌\",\"74\":\"精英光束\",\"\":0},\"info\":{\"0\":\"直线-普通\",\"1\":\"直线-普通\",\"2\":\"直线-普通\",\"3\":\"直线-普通\",\"4\":\"直线-激光\",\"5\":\"直线-激光\",\"6\":\"扩散-普通X3\",\"7\":\"散射-普通45度\",\"8\":\"直线-威力红星\",\"9\":\"直线-速射蓝星\",\"10\":\"扩散-冲击波\",\"11\":\"无攻击\",\"12\":\"高速激光\",\"13\":\"直线-针刺\",\"14\":\"波动-super\",\"15\":\"散射-激光X3\",\"16\":\"扩散-光弹X5\",\"17\":\"圆环-冲击波X6\",\"18\":\"阵列-小火箭X3\",\"19\":\"散射-蓝星X3\",\"20\":\"音爆-环干涉\",\"21\":\"直线-针刺X2\",\"22\":\"波动-super2\",\"23\":\"散射-激光X6\",\"24\":\"直线-激光\",\"25\":\"旋转-小火球\",\"26\":\"防御-绿光\",\"27\":\"前后-前后攻击\",\"28\":\"扩散-光弹X8\",\"29\":\"圆环-冲击波X8\",\"30\":\"阵列-小火箭X5\",\"31\":\"散射-蓝星\",\"32\":\"音爆-环干涉2\",\"33\":\"直线-针刺X3\",\"34\":\"交错-super3\",\"35\":\"散射-普通X10\",\"36\":\"扩散-光弹X12\",\"37\":\"圆环-冲击波X10\",\"38\":\"阵列-小火箭X7\",\"39\":\"散射-蓝星X7\",\"40\":\"音爆-环干涉3\",\"41\":\"天星乱射\",\"42\":\"超音战士\",\"43\":\"黑暗骑士\",\"44\":\"波动-super\",\"45\":\"烈火凤凰\",\"46\":\"小火箭\",\"47\":\"大火箭\",\"48\":\"敌人子弹编号\",\"49\":\"0\",\"50\":\"1\",\"51\":\"2\",\"52\":\"3\",\"53\":\"4\",\"54\":\"5\",\"55\":\"6\",\"56\":\"7\",\"57\":\"8\",\"58\":\"9\",\"59\":\"10\",\"60\":\"11\",\"61\":\"12\",\"62\":\"13\",\"63\":\"14\",\"64\":\"15\",\"65\":\"16\",\"66\":\"17\",\"67\":\"18\",\"68\":\"19\",\"69\":\"20\",\"70\":\"21\",\"71\":\"22\",\"72\":\"23\",\"73\":\"24\",\"74\":\"25\",\"\":0},\"type\":{\"0\":\"0\",\"1\":\"0\",\"2\":\"0\",\"3\":\"0\",\"4\":\"0\",\"5\":\"0\",\"6\":\"1\",\"7\":\"6\",\"8\":\"0\",\"9\":\"0\",\"10\":\"1\",\"11\":\"\",\"12\":\"0\",\"13\":\"0\",\"14\":\"7\",\"15\":\"6\",\"16\":\"1\",\"17\":\"8\",\"18\":\"0\",\"19\":\"6\",\"20\":\"9\",\"21\":\"0\",\"22\":\"7\",\"23\":\"6\",\"24\":\"0\",\"25\":\"2\",\"26\":\"3\",\"27\":\"4\",\"28\":\"1\",\"29\":\"8\",\"30\":\"1\",\"31\":\"2\",\"32\":\"9\",\"33\":\"0\",\"34\":\"7\",\"35\":\"6\",\"36\":\"1\",\"37\":\"8\",\"38\":\"1\",\"39\":\"6\",\"40\":\"9\",\"41\":\"2\",\"42\":\"1\",\"43\":\"1\",\"44\":\"7\",\"45\":\"2\",\"46\":\"0\",\"47\":\"0\",\"48\":\"注意和玩家子弹不通用\",\"49\":\"0\",\"50\":\"0\",\"51\":\"0\",\"52\":\"0\",\"53\":\"0\",\"54\":\"0\",\"55\":\"1\",\"56\":\"1\",\"57\":\"0\",\"58\":\"0\",\"59\":\"0\",\"60\":\"1\",\"61\":\"5\",\"62\":\"5\",\"63\":\"0\",\"64\":\"3\",\"65\":\"4\",\"66\":\"4\",\"67\":\"1\",\"68\":\"1\",\"69\":\"2\",\"70\":\"4\",\"71\":\"2\",\"72\":\"1\",\"73\":\"2\",\"74\":\"0\",\"\":0},\"param\":{\"0\":\"1\",\"1\":\"1\",\"2\":\"1\",\"3\":\"1\",\"4\":\"1\",\"5\":\"1\",\"6\":\"45\",\"7\":\"45\",\"8\":\"1\",\"9\":\"1\",\"10\":\"60\",\"11\":\"\",\"12\":\"1\",\"13\":\"1\",\"14\":\"30\",\"15\":\"10\",\"16\":\"25\",\"17\":\"6\",\"18\":\"0\",\"19\":\"45\",\"20\":\"120\",\"21\":\"1\",\"22\":\"45\",\"23\":\"25\",\"24\":\"1\",\"25\":\"1\",\"26\":\"0\",\"27\":\"45\",\"28\":\"20\",\"29\":\"8\",\"30\":\"0\",\"31\":\"30\",\"32\":\"200\",\"33\":\"1\",\"34\":\"60\",\"35\":\"45\",\"36\":\"15\",\"37\":\"10\",\"38\":\"2\",\"39\":\"45\",\"40\":\"300\",\"41\":\"5\",\"42\":\"90\",\"43\":\"90\",\"44\":\"15\",\"45\":\"9\",\"46\":\"0\",\"47\":\"0\",\"48\":\"\",\"49\":\"0\",\"50\":\"0\",\"51\":\"0\",\"52\":\"0\",\"53\":\"0\",\"54\":\"0\",\"55\":\"45\",\"56\":\"45\",\"57\":\"0\",\"58\":\"0\",\"59\":\"0\",\"60\":\"60\",\"61\":\"45\",\"62\":\"90\",\"63\":\"0\",\"64\":\"200\",\"65\":\"6\",\"66\":\"12\",\"67\":\"15\",\"68\":\"30\",\"69\":\"30\",\"70\":\"8\",\"71\":\"10\",\"72\":\"60\",\"73\":\"360\",\"74\":\"0\",\"\":0},\"paramExt\":{\"0\":\"0\",\"1\":\"0\",\"2\":\"0\",\"3\":\"0\",\"4\":\"0\",\"5\":\"0\",\"6\":\"1\",\"7\":\"0\",\"8\":\"0\",\"9\":\"0\",\"10\":\"0\",\"11\":\"\",\"12\":\"0\",\"13\":\"0\",\"14\":\"0\",\"15\":\"0\",\"16\":\"1\",\"17\":\"0\",\"18\":\"0\",\"19\":\"0\",\"20\":\"0\",\"21\":\"0\",\"22\":\"0\",\"23\":\"0\",\"24\":\"0\",\"25\":\"0\",\"26\":\"0\",\"27\":\"1\",\"28\":\"2\",\"29\":\"0\",\"30\":\"0\",\"31\":\"0\",\"32\":\"0\",\"33\":\"0\",\"34\":\"1\",\"35\":\"0\",\"36\":\"4\",\"37\":\"0\",\"38\":\"0\",\"39\":\"0\",\"40\":\"0\",\"41\":\"0\",\"42\":\"5\",\"43\":\"5\",\"44\":\"0\",\"45\":\"0\",\"46\":\"0\",\"47\":\"0\",\"48\":\"\",\"49\":\"0\",\"50\":\"0\",\"51\":\"0\",\"52\":\"0\",\"53\":\"0\",\"54\":\"0\",\"55\":\"3\",\"56\":\"3\",\"57\":\"0\",\"58\":\"0\",\"59\":\"0\",\"60\":\"2\",\"61\":\"1\",\"62\":\"1\",\"63\":\"0\",\"64\":\"1\",\"65\":\"0\",\"66\":\"0\",\"67\":\"2\",\"68\":\"2\",\"69\":\"0\",\"70\":\"3\",\"71\":\"0\",\"72\":\"5\",\"73\":\"2\",\"74\":\"0\",\"\":0},\"animation\":{\"0\":\"speed\",\"1\":\"speed\",\"2\":\"speed\",\"3\":\"speed\",\"4\":\"laser\",\"5\":\"laser\",\"6\":\"mini\",\"7\":\"mini\",\"8\":\"star_red\",\"9\":\"star_blue\",\"10\":\"wave\",\"11\":\"\",\"12\":\"laser\",\"13\":\"needle\",\"14\":\"super\",\"15\":\"laser\",\"16\":\"light\",\"17\":\"wave\",\"18\":\"rocket1\",\"19\":\"star_blue\",\"20\":\"water\",\"21\":\"needle\",\"22\":\"super\",\"23\":\"laser\",\"24\":\"laser\",\"25\":\"fire\",\"26\":\"Default\",\"27\":\"speed\",\"28\":\"light\",\"29\":\"wave\",\"30\":\"rocket1\",\"31\":\"star_blue\",\"32\":\"water\",\"33\":\"needle\",\"34\":\"super\",\"35\":\"laser\",\"36\":\"light\",\"37\":\"wave\",\"38\":\"rocket1\",\"39\":\"star_blue\",\"40\":\"water\",\"41\":\"star\",\"42\":\"super_water\",\"43\":\"super_dark\",\"44\":\"dark\",\"45\":\"fire\",\"46\":\"rocket1\",\"47\":\"rocket2\",\"48\":\"\",\"49\":\"ball\",\"50\":\"ball\",\"51\":\"ball\",\"52\":\"thorn\",\"53\":\"ball\",\"54\":\"ball\",\"55\":\"light\",\"56\":\"light\",\"57\":\"thunder\",\"58\":\"thunder\",\"59\":\"crystal\",\"60\":\"crystal\",\"61\":\"noraml\",\"62\":\"noraml\",\"63\":\"normal\",\"64\":\"dark\",\"65\":\"red\",\"66\":\"normal\",\"67\":\"thorn\",\"68\":\"normal\",\"69\":\"ice\",\"70\":\"red\",\"71\":\"thorn\",\"72\":\"green\",\"73\":\"superdark\",\"74\":\"superball\",\"\":0},\"baseDmg\":{\"0\":\"1\",\"1\":\"1\",\"2\":\"1\",\"3\":\"1\",\"4\":\"1\",\"5\":\"1\",\"6\":\"1\",\"7\":\"1\",\"8\":\"1\",\"9\":\"1\",\"10\":\"1\",\"11\":\"\",\"12\":\"0\",\"13\":\"1\",\"14\":\"1\",\"15\":\"1\",\"16\":\"1\",\"17\":\"1\",\"18\":\"1\",\"19\":\"1\",\"20\":\"1\",\"21\":\"1\",\"22\":\"1\",\"23\":\"1\",\"24\":\"1\",\"25\":\"1\",\"26\":\"1\",\"27\":\"1\",\"28\":\"1\",\"29\":\"1\",\"30\":\"1\",\"31\":\"1\",\"32\":\"1\",\"33\":\"1\",\"34\":\"1\",\"35\":\"1\",\"36\":\"1\",\"37\":\"1\",\"38\":\"1\",\"39\":\"1\",\"40\":\"1\",\"41\":\"1\",\"42\":\"1\",\"43\":\"1\",\"44\":\"1\",\"45\":\"1\",\"46\":\"1\",\"47\":\"1\",\"48\":\"\",\"49\":\"1\",\"50\":\"1\",\"51\":\"1\",\"52\":\"1\",\"53\":\"1\",\"54\":\"1\",\"55\":\"1\",\"56\":\"1\",\"57\":\"1\",\"58\":\"1\",\"59\":\"1\",\"60\":\"1\",\"61\":\"1\",\"62\":\"1\",\"63\":\"1\",\"64\":\"1\",\"65\":\"1\",\"66\":\"1\",\"67\":\"1\",\"68\":\"1\",\"69\":\"1\",\"70\":\"1\",\"71\":\"1\",\"72\":\"1\",\"73\":\"1\",\"74\":\"1\",\"\":0},\"hit\":{\"0\":\"0\",\"1\":\"0\",\"2\":\"0\",\"3\":\"0\",\"4\":\"0\",\"5\":\"0\",\"6\":\"0\",\"7\":\"0\",\"8\":\"0\",\"9\":\"0\",\"10\":\"0\",\"11\":\"\",\"12\":\"0\",\"13\":\"0\",\"14\":\"0\",\"15\":\"0\",\"16\":\"0\",\"17\":\"0\",\"18\":\"0\",\"19\":\"0\",\"20\":\"0\",\"21\":\"0\",\"22\":\"0\",\"23\":\"0\",\"24\":\"0\",\"25\":\"0\",\"26\":\"0\",\"27\":\"0\",\"28\":\"0\",\"29\":\"0\",\"30\":\"0\",\"31\":\"0\",\"32\":\"0\",\"33\":\"0\",\"34\":\"0\",\"35\":\"0\",\"36\":\"0\",\"37\":\"0\",\"38\":\"0\",\"39\":\"0\",\"40\":\"0\",\"41\":\"0\",\"42\":\"0\",\"43\":\"0\",\"44\":\"0\",\"45\":\"0\",\"46\":\"0\",\"47\":\"0\",\"48\":\"\",\"49\":\"0\",\"50\":\"0\",\"51\":\"0\",\"52\":\"0\",\"53\":\"0\",\"54\":\"0\",\"55\":\"0\",\"56\":\"0\",\"57\":\"0\",\"58\":\"0\",\"59\":\"0\",\"60\":\"0\",\"61\":\"0\",\"62\":\"0\",\"63\":\"0\",\"64\":\"0\",\"65\":\"0\",\"66\":\"0\",\"67\":\"0\",\"68\":\"0\",\"69\":\"0\",\"70\":\"0\",\"71\":\"0\",\"72\":\"0\",\"73\":\"0\",\"74\":\"0\",\"\":0},\"speed\":{\"0\":\"200\",\"1\":\"200\",\"2\":\"200\",\"3\":\"200\",\"4\":\"400\",\"5\":\"400\",\"6\":\"200\",\"7\":\"100\",\"8\":\"150\",\"9\":\"300\",\"10\":\"100\",\"11\":\"\",\"12\":\"500\",\"13\":\"500\",\"14\":\"200\",\"15\":\"400\",\"16\":\"400\",\"17\":\"100\",\"18\":\"100\",\"19\":\"200\",\"20\":\"100\",\"21\":\"500\",\"22\":\"200\",\"23\":\"400\",\"24\":\"400\",\"25\":\"400\",\"26\":\"100\",\"27\":\"100\",\"28\":\"400\",\"29\":\"100\",\"30\":\"100\",\"31\":\"300\",\"32\":\"300\",\"33\":\"500\",\"34\":\"200\",\"35\":\"100\",\"36\":\"400\",\"37\":\"100\",\"38\":\"100\",\"39\":\"250\",\"40\":\"100\",\"41\":\"200\",\"42\":\"200\",\"43\":\"100\",\"44\":\"200\",\"45\":\"200\",\"46\":\"100\",\"47\":\"100\",\"48\":\"\",\"49\":\"100\",\"50\":\"100\",\"51\":\"100\",\"52\":\"200\",\"53\":\"100\",\"54\":\"100\",\"55\":\"100\",\"56\":\"100\",\"57\":\"100\",\"58\":\"150\",\"59\":\"150\",\"60\":\"100\",\"61\":\"100\",\"62\":\"100\",\"63\":\"100\",\"64\":\"100\",\"65\":\"100\",\"66\":\"100\",\"67\":\"250\",\"68\":\"100\",\"69\":\"100\",\"70\":\"100\",\"71\":\"200\",\"72\":\"100\",\"73\":\"200\",\"74\":\"500\",\"\":0},\"rate\":{\"0\":\"800\",\"1\":\"800\",\"2\":\"800\",\"3\":\"800\",\"4\":\"1000\",\"5\":\"1000\",\"6\":\"800\",\"7\":\"1000\",\"8\":\"1000\",\"9\":\"1000\",\"10\":\"600\",\"11\":\"\",\"12\":\"400\",\"13\":\"300\",\"14\":\"500\",\"15\":\"1000\",\"16\":\"700\",\"17\":\"1000\",\"18\":\"1000\",\"19\":\"1000\",\"20\":\"1000\",\"21\":\"500\",\"22\":\"1000\",\"23\":\"1000\",\"24\":\"1000\",\"25\":\"1000\",\"26\":\"1000\",\"27\":\"1000\",\"28\":\"700\",\"29\":\"1000\",\"30\":\"500\",\"31\":\"1000\",\"32\":\"500\",\"33\":\"700\",\"34\":\"700\",\"35\":\"1000\",\"36\":\"700\",\"37\":\"1000\",\"38\":\"1000\",\"39\":\"1000\",\"40\":\"1000\",\"41\":\"1000\",\"42\":\"1000\",\"43\":\"1000\",\"44\":\"500\",\"45\":\"500\",\"46\":\"1000\",\"47\":\"1000\",\"48\":\"\",\"49\":\"600\",\"50\":\"600\",\"51\":\"800\",\"52\":\"800\",\"53\":\"200\",\"54\":\"500\",\"55\":\"600\",\"56\":\"600\",\"57\":\"600\",\"58\":\"600\",\"59\":\"600\",\"60\":\"600\",\"61\":\"600\",\"62\":\"600\",\"63\":\"600\",\"64\":\"600\",\"65\":\"600\",\"66\":\"600\",\"67\":\"600\",\"68\":\"600\",\"69\":\"600\",\"70\":\"600\",\"71\":\"600\",\"72\":\"600\",\"73\":\"600\",\"74\":\"800\",\"\":0},\"dmg\":{\"0\":\"1\",\"1\":\"1\",\"2\":\"1\",\"3\":\"1\",\"4\":\"2\",\"5\":\"2\",\"6\":\"1\",\"7\":\"1\",\"8\":\"2\",\"9\":\"1.2\",\"10\":\"1\",\"11\":\"\",\"12\":\"1\",\"13\":\"1\",\"14\":\"1.6\",\"15\":\"1.8\",\"16\":\"1.4\",\"17\":\"1.6\",\"18\":\"1.6\",\"19\":\"1.6\",\"20\":\"3\",\"21\":\"1.2\",\"22\":\"2.2\",\"23\":\"2\",\"24\":\"1.8\",\"25\":\"3.2\",\"26\":\"2\",\"27\":\"2\",\"28\":\"1.8\",\"29\":\"2\",\"30\":\"2.4\",\"31\":\"2\",\"32\":\"3.5\",\"33\":\"1.4\",\"34\":\"2.4\",\"35\":\"2.2\",\"36\":\"2\",\"37\":\"2\",\"38\":\"3.2\",\"39\":\"3\",\"40\":\"4\",\"41\":\"4\",\"42\":\"2\",\"43\":\"2\",\"44\":\"4\",\"45\":\"2\",\"46\":\"2\",\"47\":\"2\",\"48\":\"\",\"49\":\"1\",\"50\":\"1\",\"51\":\"1\",\"52\":\"1\",\"53\":\"1\",\"54\":\"1\",\"55\":\"1\",\"56\":\"1\",\"57\":\"1\",\"58\":\"0.8\",\"59\":\"1\",\"60\":\"1\",\"61\":\"1\",\"62\":\"1\",\"63\":\"1\",\"64\":\"1\",\"65\":\"1\",\"66\":\"1\",\"67\":\"1.2\",\"68\":\"2\",\"69\":\"2\",\"70\":\"2\",\"71\":\"2\",\"72\":\"2\",\"73\":\"4\",\"74\":\"4\",\"\":0},\"isThrough\":{\"0\":\"0\",\"1\":\"0\",\"2\":\"0\",\"3\":\"0\",\"4\":\"1\",\"5\":\"1\",\"6\":\"0\",\"7\":\"0\",\"8\":\"1\",\"9\":\"1\",\"10\":\"0\",\"11\":\"\",\"12\":\"0\",\"13\":\"1\",\"14\":\"1\",\"15\":\"1\",\"16\":\"0\",\"17\":\"0\",\"18\":\"0\",\"19\":\"0\",\"20\":\"0\",\"21\":\"1\",\"22\":\"0\",\"23\":\"1\",\"24\":\"1\",\"25\":\"1\",\"26\":\"0\",\"27\":\"0\",\"28\":\"0\",\"29\":\"0\",\"30\":\"0\",\"31\":\"1\",\"32\":\"1\",\"33\":\"1\",\"34\":\"1\",\"35\":\"0\",\"36\":\"0\",\"37\":\"0\",\"38\":\"0\",\"39\":\"0\",\"40\":\"0\",\"41\":\"1\",\"42\":\"1\",\"43\":\"1\",\"44\":\"1\",\"45\":\"1\",\"46\":\"0\",\"47\":\"0\",\"48\":\"\",\"49\":\"0\",\"50\":\"0\",\"51\":\"0\",\"52\":\"1\",\"53\":\"1\",\"54\":\"1\",\"55\":\"0\",\"56\":\"0\",\"57\":\"0\",\"58\":\"0\",\"59\":\"1\",\"60\":\"1\",\"61\":\"0\",\"62\":\"0\",\"63\":\"1\",\"64\":\"1\",\"65\":\"1\",\"66\":\"1\",\"67\":\"1\",\"68\":\"0\",\"69\":\"0\",\"70\":\"0\",\"71\":\"1\",\"72\":\"0\",\"73\":\"1\",\"74\":\"1\",\"\":0},\"\":{\"0\":\"\",\"1\":\"\",\"2\":\"\",\"3\":\"\",\"4\":\"\",\"5\":\"\",\"6\":\"\",\"7\":\"\",\"8\":\"\",\"9\":\"\",\"10\":\"\",\"11\":\"\",\"12\":\"\",\"13\":\"\",\"14\":\"\",\"15\":\"\",\"16\":\"\",\"17\":\"\",\"18\":\"\",\"19\":\"\",\"20\":\"\",\"21\":\"\",\"22\":\"\",\"23\":\"\",\"24\":\"\",\"25\":\"\",\"26\":\"\",\"27\":\"\",\"28\":\"\",\"29\":\"\",\"30\":\"\",\"31\":\"\",\"32\":\"\",\"33\":\"\",\"34\":\"\",\"35\":\"\",\"36\":\"\",\"37\":\"\",\"38\":\"\",\"39\":\"\",\"40\":\"\",\"41\":\"\",\"42\":\"\",\"43\":\"\",\"44\":\"\",\"45\":\"\",\"46\":\"\",\"47\":\"\",\"48\":\"\",\"49\":\"\",\"50\":\"\",\"51\":\"\",\"52\":\"\",\"53\":\"\",\"54\":\"\",\"55\":\"\",\"56\":\"\",\"57\":\"\",\"58\":\"\",\"59\":\"\",\"60\":\"\",\"61\":\"\",\"62\":\"\",\"63\":\"\",\"64\":\"\",\"65\":\"\",\"66\":\"\",\"67\":\"\",\"68\":\"\",\"69\":\"\",\"70\":\"\",\"71\":\"\",\"72\":\"\",\"73\":\"\",\"74\":\"\",\"\":0}},\"keys\":[\"name\",\"info\",\"type\",\"param\",\"paramExt\",\"animation\",\"baseDmg\",\"hit\",\"speed\",\"rate\",\"dmg\",\"isThrough\",\"\"],\"items\":[\"0\",\"1\",\"2\",\"3\",\"4\",\"5\",\"6\",\"7\",\"8\",\"9\",\"10\",\"11\",\"12\",\"13\",\"14\",\"15\",\"16\",\"17\",\"18\",\"19\",\"20\",\"21\",\"22\",\"23\",\"24\",\"25\",\"26\",\"27\",\"28\",\"29\",\"30\",\"31\",\"32\",\"33\",\"34\",\"35\",\"36\",\"37\",\"38\",\"39\",\"40\",\"41\",\"42\",\"43\",\"44\",\"45\",\"46\",\"47\",\"48\",\"49\",\"50\",\"51\",\"52\",\"53\",\"54\",\"55\",\"56\",\"57\",\"58\",\"59\",\"60\",\"61\",\"62\",\"63\",\"64\",\"65\",\"66\",\"67\",\"68\",\"69\",\"70\",\"71\",\"72\",\"73\",\"74\",\"\"]}","plane":"{\"table\":{\"name\":{\"0\":\"红蝠-X\",\"1\":\"寒冰-M\",\"2\":\"蓝光-D\",\"3\":\"疾风-W\",\"4\":\"紫塔激光炮\",\"5\":\"红石激光炮\",\"6\":\"钢铁扩散器\",\"7\":\"钢铁散射器\",\"8\":\"热焰号\",\"9\":\"时光号\",\"10\":\"能量号\",\"11\":\"傀儡\",\"12\":\"光球\",\"13\":\"食人花\",\"14\":\"红钢\",\"15\":\"海神\",\"16\":\"恶梦\",\"17\":\"神龙\",\"18\":\"审判者\",\"19\":\"亚瑟\",\"20\":\"噪音\",\"21\":\"食人花2号\",\"22\":\"红钢2号\",\"23\":\"海神2号\",\"24\":\"黄蜂号\",\"25\":\"红蜘蛛\",\"26\":\"绿甲虫\",\"27\":\"幽灵蜘蛛\",\"28\":\"恶梦2号\",\"29\":\"神龙2号\",\"30\":\"审判者2号\",\"31\":\"亚瑟2号\",\"32\":\"噪音2号\",\"33\":\"食人花3号\",\"34\":\"红钢3号\",\"35\":\"海神3号\",\"36\":\"恶梦3号\",\"37\":\"神龙3号\",\"38\":\"审判者3号\",\"39\":\"亚瑟3号\",\"40\":\"噪音3号\",\"41\":\"天使护卫\",\"42\":\"超音战士\",\"43\":\"黑暗骑士\",\"44\":\"霹雳巨钳\",\"45\":\"烈火凤凰\",\"\":0},\"title\":{\"0\":\"首架飞机\",\"1\":\"冰冻\",\"2\":\"蓝色\",\"3\":\"突破疾风\",\"4\":\"激光武器\",\"5\":\"激光武器\",\"6\":\"扩散射击\",\"7\":\"持续散射\",\"8\":\"红色光弹\",\"9\":\"蓝色光弹\",\"10\":\"黄色光弹\",\"11\":\"肉盾\",\"12\":\"激光武器\",\"13\":\"光合作用\",\"14\":\"光弹曲折\",\"15\":\"海神\",\"16\":\"恶梦降临\",\"17\":\"震荡波动\",\"18\":\"导弹\",\"19\":\"传奇\",\"20\":\"冲击波\",\"21\":\"光合作用\",\"22\":\"光弹曲折\",\"23\":\"海神\",\"24\":\"高速针刺\",\"25\":\"火球\",\"26\":\"防御系\",\"27\":\"前后发射\",\"28\":\"恶梦降临\",\"29\":\"震荡波动\",\"30\":\"导弹\",\"31\":\"传奇\",\"32\":\"冲击波\",\"33\":\"光合作用\",\"34\":\"光弹曲折\",\"35\":\"海神\",\"36\":\"恶梦降临\",\"37\":\"震荡波动\",\"38\":\"导弹\",\"39\":\"传奇\",\"40\":\"冲击波\",\"41\":\"超级星星\",\"42\":\"隐匿\",\"43\":\"黑暗球\",\"44\":\"波动弹\",\"45\":\"重生之炎\",\"\":0},\"info\":{\"0\":\"基础飞机\\\\射速快\\\\但伤害低。\",\"1\":\"基础的飞机\\\\射速慢\\\\但伤害高。\",\"2\":\"基础飞机\\\\能力比较均衡。\",\"3\":\"基础飞机\\\\生命低\\\\但射速快\",\"4\":\"发射高速激光弹攻击。\",\"5\":\"发射高速激光弹攻击。\",\"6\":\"扩散发射子弹\\\\威力弱\\\\但是对付散乱的杂兵比较有效。\",\"7\":\"高速连续发射子弹。威力弱\\\\但是对付难缠的敌人占据优势。\",\"8\":\"发射红色星星攻击\\\\威力较高。\",\"9\":\"发射蓝色星星攻击\\\\速度较快。\",\"10\":\"发射黄色星星攻击\\\\比较均衡。\",\"11\":\"无法发动攻击\\\\但是体力高\\\\也只能当肉盾使用。\",\"12\":\"发射激光的球体\\\\勉强算是飞船吧。\",\"13\":\"吸收太阳光能量\\\\会发射急速的针刺。\",\"14\":\"飞船坚固的飞船\\\\发生弯曲变化的光弹。\",\"15\":\"发射缓慢的散射激光。\",\"16\":\"产生扩散的能量光弹。\",\"17\":\"发射环状的冲击波子弹。\",\"18\":\"发射推进加速的导弹。\",\"19\":\"发射散射的能量波动。\",\"20\":\"大范围的音波对敌人造成伤害。\",\"21\":\"食人花号改进版本\\\\性能增强了些\\\\发射针刺攻击。\",\"22\":\"相对初代版本强化了攻击力\\\\高速发射弯曲变化的光弹。\",\"23\":\"发射缓慢的散射激光。海神强化版\\\\能力有所提升。\",\"24\":\"移动非常灵活\\\\而且子弹也射速极快\",\"25\":\"伤害较高\\\\能发射贯穿的火球子弹。\",\"26\":\"能够反弹敌人发射的子弹。\",\"27\":\"向前后方向都会发射子弹的类型\\\\非常灵活。\",\"28\":\"在周围产生能量球环绕\\\\一定时候后扩散开来。\",\"29\":\"发射环状冲击波子弹\\\\范围比起初代大。\",\"30\":\"发射推进加速的导弹。相对初代能力有所上升。\",\"31\":\"发射散射的能量波动。相对初代能力有所上升。\",\"32\":\"噪音2号强化版\\\\属性所有提升\\\\大范围的音波对敌人造成伤害。\",\"33\":\"食人花号强化版\\\\属性所有提升\\\\会发生急速的针刺攻击。\",\"34\":\"相对初代能力大幅提升\\\\发射高速弯曲变化的光弹。\",\"35\":\"发射缓慢的散射激光。能力相对于海神2号有着明显提升。\",\"36\":\"在周围产生能量球环绕\\\\一定时候后扩散开来。\",\"37\":\"发射环状冲击波子弹\\\\目前改进后能力得到大幅的提升。\",\"38\":\"发射散射导弹。相对初代能力大幅提升。\",\"39\":\"发射散射的能量波动。相对初代能力大幅提升。\",\"40\":\"大范围的音波对敌人造成伤害。相对初代能力大幅提升。\",\"41\":\"生命较多\\\\发射威力较高速度较快的流星攻击。\",\"42\":\"被攻击后\\\\会进入隐身状态\\\\此时不会被任何子弹击中。\",\"43\":\"持续快速发射黑暗球攻击\\\\每一击的威力都十分强大\",\"44\":\"持续散射黑暗波动弹的的BOSS级攻击。\",\"45\":\"从浴火中重生吧！\\\\能发出强烈多方向火球攻击。\",\"\":0},\"rank\":{\"0\":\"1\",\"1\":\"1\",\"2\":\"1\",\"3\":\"1\",\"4\":\"1\",\"5\":\"1\",\"6\":\"1\",\"7\":\"1\",\"8\":\"1\",\"9\":\"1\",\"10\":\"1\",\"11\":\"1\",\"12\":\"1\",\"13\":\"2\",\"14\":\"2\",\"15\":\"2\",\"16\":\"2\",\"17\":\"2\",\"18\":\"2\",\"19\":\"2\",\"20\":\"2\",\"21\":\"3\",\"22\":\"3\",\"23\":\"3\",\"24\":\"3\",\"25\":\"3\",\"26\":\"3\",\"27\":\"3\",\"28\":\"3\",\"29\":\"3\",\"30\":\"3\",\"31\":\"3\",\"32\":\"3\",\"33\":\"4\",\"34\":\"4\",\"35\":\"4\",\"36\":\"4\",\"37\":\"4\",\"38\":\"4\",\"39\":\"4\",\"40\":\"4\",\"41\":\"5\",\"42\":\"5\",\"43\":\"5\",\"44\":\"5\",\"45\":\"5\",\"\":0},\"skinId\":{\"0\":\"0\",\"1\":\"1\",\"2\":\"2\",\"3\":\"3\",\"4\":\"4\",\"5\":\"5\",\"6\":\"6\",\"7\":\"7\",\"8\":\"8\",\"9\":\"9\",\"10\":\"10\",\"11\":\"11\",\"12\":\"12\",\"13\":\"0\",\"14\":\"1\",\"15\":\"2\",\"16\":\"3\",\"17\":\"4\",\"18\":\"5\",\"19\":\"6\",\"20\":\"7\",\"21\":\"0\",\"22\":\"1\",\"23\":\"2\",\"24\":\"3\",\"25\":\"4\",\"26\":\"5\",\"27\":\"6\",\"28\":\"7\",\"29\":\"8\",\"30\":\"9\",\"31\":\"10\",\"32\":\"11\",\"33\":\"0\",\"34\":\"1\",\"35\":\"2\",\"36\":\"3\",\"37\":\"4\",\"38\":\"5\",\"39\":\"6\",\"40\":\"7\",\"41\":\"0\",\"42\":\"1\",\"43\":\"2\",\"44\":\"3\",\"45\":\"4\",\"\":0},\"atk\":{\"0\":\"10\",\"1\":\"20\",\"2\":\"10\",\"3\":\"5\",\"4\":\"10\",\"5\":\"20\",\"6\":\"20\",\"7\":\"0\",\"8\":\"35\",\"9\":\"35\",\"10\":\"20\",\"11\":\"0\",\"12\":\"0\",\"13\":\"20\",\"14\":\"20\",\"15\":\"20\",\"16\":\"40\",\"17\":\"50\",\"18\":\"10\",\"19\":\"10\",\"20\":\"10\",\"21\":\"10\",\"22\":\"50\",\"23\":\"10\",\"24\":\"10\",\"25\":\"10\",\"26\":\"10\",\"27\":\"10\",\"28\":\"10\",\"29\":\"60\",\"30\":\"10\",\"31\":\"10\",\"32\":\"10\",\"33\":\"10\",\"34\":\"50\",\"35\":\"10\",\"36\":\"30\",\"37\":\"80\",\"38\":\"100\",\"39\":\"10\",\"40\":\"10\",\"41\":\"10\",\"42\":\"10\",\"43\":\"30\",\"44\":\"10\",\"45\":\"70\",\"\":0},\"hp\":{\"0\":\"20\",\"1\":\"10\",\"2\":\"10\",\"3\":\"5\",\"4\":\"10\",\"5\":\"5\",\"6\":\"10\",\"7\":\"15\",\"8\":\"15\",\"9\":\"20\",\"10\":\"30\",\"11\":\"50\",\"12\":\"15\",\"13\":\"30\",\"14\":\"40\",\"15\":\"35\",\"16\":\"20\",\"17\":\"30\",\"18\":\"50\",\"19\":\"50\",\"20\":\"35\",\"21\":\"30\",\"22\":\"40\",\"23\":\"35\",\"24\":\"50\",\"25\":\"40\",\"26\":\"65\",\"27\":\"40\",\"28\":\"50\",\"29\":\"45\",\"30\":\"50\",\"31\":\"55\",\"32\":\"50\",\"33\":\"65\",\"34\":\"50\",\"35\":\"60\",\"36\":\"70\",\"37\":\"60\",\"38\":\"80\",\"39\":\"100\",\"40\":\"85\",\"41\":\"120\",\"42\":\"140\",\"43\":\"180\",\"44\":\"160\",\"45\":\"200\",\"\":0},\"moveSpeed\":{\"0\":\"10\",\"1\":\"20\",\"2\":\"20\",\"3\":\"60\",\"4\":\"20\",\"5\":\"30\",\"6\":\"30\",\"7\":\"20\",\"8\":\"20\",\"9\":\"20\",\"10\":\"20\",\"11\":\"0\",\"12\":\"50\",\"13\":\"20\",\"14\":\"30\",\"15\":\"40\",\"16\":\"30\",\"17\":\"20\",\"18\":\"20\",\"19\":\"20\",\"20\":\"65\",\"21\":\"20\",\"22\":\"40\",\"23\":\"60\",\"24\":\"20\",\"25\":\"20\",\"26\":\"20\",\"27\":\"20\",\"28\":\"40\",\"29\":\"20\",\"30\":\"20\",\"31\":\"30\",\"32\":\"35\",\"33\":\"20\",\"34\":\"40\",\"35\":\"80\",\"36\":\"40\",\"37\":\"20\",\"38\":\"20\",\"39\":\"40\",\"40\":\"60\",\"41\":\"20\",\"42\":\"80\",\"43\":\"40\",\"44\":\"20\",\"45\":\"60\",\"\":0},\"shootSpeed\":{\"0\":\"0.4\",\"1\":\"0.4\",\"2\":\"0.4\",\"3\":\"0.5\",\"4\":\"0.8\",\"5\":\"0.8\",\"6\":\"1\",\"7\":\"0.25\",\"8\":\"0.5\",\"9\":\"0.5\",\"10\":\"0.5\",\"11\":\"0.8\",\"12\":\"0.4\",\"13\":\"0.3\",\"14\":\"0.5\",\"15\":\"0.3\",\"16\":\"0.9\",\"17\":\"1\",\"18\":\"0.8\",\"19\":\"1\",\"20\":\"1\",\"21\":\"0.15\",\"22\":\"0.4\",\"23\":\"0.2\",\"24\":\"0.2\",\"25\":\"0.8\",\"26\":\"0.8\",\"27\":\"1\",\"28\":\"0.8\",\"29\":\"0.9\",\"30\":\"0.5\",\"31\":\"0.8\",\"32\":\"0.8\",\"33\":\"0.15\",\"34\":\"0.1\",\"35\":\"0.2\",\"36\":\"0.6\",\"37\":\"0.8\",\"38\":\"0.3\",\"39\":\"0.8\",\"40\":\"1\",\"41\":\"1.2\",\"42\":\"0.7\",\"43\":\"0.5\",\"44\":\"0.2\",\"45\":\"1.2\",\"\":0},\"bulletId\":{\"0\":\"0\",\"1\":\"1\",\"2\":\"2\",\"3\":\"3\",\"4\":\"4\",\"5\":\"5\",\"6\":\"6\",\"7\":\"7\",\"8\":\"8\",\"9\":\"9\",\"10\":\"10\",\"11\":\"11\",\"12\":\"12\",\"13\":\"13\",\"14\":\"14\",\"15\":\"15\",\"16\":\"16\",\"17\":\"17\",\"18\":\"18\",\"19\":\"20\",\"20\":\"19\",\"21\":\"21\",\"22\":\"22\",\"23\":\"23\",\"24\":\"24\",\"25\":\"25\",\"26\":\"26\",\"27\":\"27\",\"28\":\"28\",\"29\":\"29\",\"30\":\"30\",\"31\":\"31\",\"32\":\"32\",\"33\":\"33\",\"34\":\"34\",\"35\":\"35\",\"36\":\"36\",\"37\":\"37\",\"38\":\"38\",\"39\":\"39\",\"40\":\"40\",\"41\":\"41\",\"42\":\"42\",\"43\":\"43\",\"44\":\"44\",\"45\":\"45\",\"\":0},\"gold\":{\"0\":\"150\",\"1\":\"200\",\"2\":\"300\",\"3\":\"250\",\"4\":\"400\",\"5\":\"450\",\"6\":\"500\",\"7\":\"600\",\"8\":\"1000\",\"9\":\"1000\",\"10\":\"1000\",\"11\":\"1000\",\"12\":\"1000\",\"13\":\"1200\",\"14\":\"1400\",\"15\":\"1600\",\"16\":\"1200\",\"17\":\"1600\",\"18\":\"1280\",\"19\":\"1000\",\"20\":\"1800\",\"21\":\"2400\",\"22\":\"3000\",\"23\":\"2050\",\"24\":\"1800\",\"25\":\"2400\",\"26\":\"2550\",\"27\":\"2240\",\"28\":\"2480\",\"29\":\"3500\",\"30\":\"2800\",\"31\":\"2660\",\"32\":\"3600\",\"33\":\"3600\",\"34\":\"4400\",\"35\":\"4800\",\"36\":\"5000\",\"37\":\"4200\",\"38\":\"5200\",\"39\":\"4200\",\"40\":\"6666\",\"41\":\"7500\",\"42\":\"8000\",\"43\":\"9500\",\"44\":\"9999\",\"45\":\"15000\",\"\":0},\"rateValue\":{\"0\":\"100\",\"1\":\"100\",\"2\":\"100\",\"3\":\"100\",\"4\":\"100\",\"5\":\"100\",\"6\":\"100\",\"7\":\"100\",\"8\":\"100\",\"9\":\"100\",\"10\":\"75\",\"11\":\"50\",\"12\":\"50\",\"13\":\"50\",\"14\":\"50\",\"15\":\"45\",\"16\":\"45\",\"17\":\"30\",\"18\":\"30\",\"19\":\"20\",\"20\":\"30\",\"21\":\"30\",\"22\":\"20\",\"23\":\"30\",\"24\":\"10\",\"25\":\"30\",\"26\":\"30\",\"27\":\"30\",\"28\":\"20\",\"29\":\"30\",\"30\":\"30\",\"31\":\"10\",\"32\":\"30\",\"33\":\"30\",\"34\":\"15\",\"35\":\"20\",\"36\":\"10\",\"37\":\"10\",\"38\":\"10\",\"39\":\"10\",\"40\":\"10\",\"41\":\"5\",\"42\":\"5\",\"43\":\"5\",\"44\":\"5\",\"45\":\"5\",\"\":0},\"group\":{\"0\":\"init\",\"1\":\"init\",\"2\":\"init\",\"3\":\"init\",\"4\":\"init\",\"5\":\"init\",\"6\":\"init\",\"7\":\"init\",\"8\":\"init\",\"9\":\"init\",\"10\":\"init\",\"11\":\"\",\"12\":\"\",\"13\":\"\",\"14\":\"\",\"15\":\"\",\"16\":\"\",\"17\":\"\",\"18\":\"\",\"19\":\"\",\"20\":\"\",\"21\":\"\",\"22\":\"\",\"23\":\"\",\"24\":\"\",\"25\":\"\",\"26\":\"\",\"27\":\"\",\"28\":\"\",\"29\":\"\",\"30\":\"\",\"31\":\"\",\"32\":\"\",\"33\":\"\",\"34\":\"\",\"35\":\"\",\"36\":\"\",\"37\":\"\",\"38\":\"\",\"39\":\"\",\"40\":\"\",\"41\":\"\",\"42\":\"\",\"43\":\"\",\"44\":\"\",\"45\":\"\",\"\":0},\"\":{\"0\":\"\",\"1\":\"\",\"2\":\"\",\"3\":\"\",\"4\":\"\",\"5\":\"\",\"6\":\"\",\"7\":\"\",\"8\":\"\",\"9\":\"\",\"10\":\"\",\"11\":\"\",\"12\":\"\",\"13\":\"\",\"14\":\"\",\"15\":\"\",\"16\":\"\",\"17\":\"\",\"18\":\"\",\"19\":\"\",\"20\":\"\",\"21\":\"\",\"22\":\"\",\"23\":\"\",\"24\":\"\",\"25\":\"\",\"26\":\"\",\"27\":\"\",\"28\":\"\",\"29\":\"\",\"30\":\"\",\"31\":\"\",\"32\":\"\",\"33\":\"\",\"34\":\"\",\"35\":\"\",\"36\":\"\",\"37\":\"\",\"38\":\"\",\"39\":\"\",\"40\":\"\",\"41\":\"\",\"42\":\"\",\"43\":\"\",\"44\":\"\",\"45\":\"\",\"\":0},\"debug\":{\"0\":\"90\",\"1\":\"100\",\"2\":\"90\",\"3\":\"110\",\"4\":\"65\",\"5\":\"80\",\"6\":\"80\",\"7\":\"115\",\"8\":\"110\",\"9\":\"115\",\"10\":\"110\",\"11\":\"75\",\"12\":\"115\",\"13\":\"136.666666667\",\"14\":\"130\",\"15\":\"161.666666667\",\"16\":\"112.222222222\",\"17\":\"120\",\"18\":\"105\",\"19\":\"100\",\"20\":\"130\",\"21\":\"193.333333333\",\"22\":\"180\",\"23\":\"205\",\"24\":\"180\",\"25\":\"95\",\"26\":\"120\",\"27\":\"90\",\"28\":\"125\",\"29\":\"147.222222222\",\"30\":\"120\",\"31\":\"120\",\"32\":\"120\",\"33\":\"228.333333333\",\"34\":\"340\",\"35\":\"250\",\"36\":\"173.333333333\",\"37\":\"185\",\"38\":\"266.666666667\",\"39\":\"175\",\"40\":\"175\",\"41\":\"166.666666667\",\"42\":\"258.571428571\",\"43\":\"290\",\"44\":\"290\",\"45\":\"346.666666667\",\"\":0}},\"keys\":[\"name\",\"title\",\"info\",\"rank\",\"skinId\",\"atk\",\"hp\",\"moveSpeed\",\"shootSpeed\",\"bulletId\",\"gold\",\"rateValue\",\"group\",\"\",\"debug\"],\"items\":[\"0\",\"1\",\"2\",\"3\",\"4\",\"5\",\"6\",\"7\",\"8\",\"9\",\"10\",\"11\",\"12\",\"13\",\"14\",\"15\",\"16\",\"17\",\"18\",\"19\",\"20\",\"21\",\"22\",\"23\",\"24\",\"25\",\"26\",\"27\",\"28\",\"29\",\"30\",\"31\",\"32\",\"33\",\"34\",\"35\",\"36\",\"37\",\"38\",\"39\",\"40\",\"41\",\"42\",\"43\",\"44\",\"45\",\"\"]}","enemy":"{\"table\":{\"name\":{\"0\":\"紫色量产\",\"1\":\"红色量产\",\"2\":\"蓝色量产\",\"3\":\"突刺探测机\",\"4\":\"旋转刺刃\",\"5\":\"游荡幽灵\",\"6\":\"绿色装甲\",\"7\":\"蓝色装甲\",\"8\":\"装载机\",\"9\":\"瑟雷夫\",\"10\":\"幻影魔晶\",\"11\":\"紫色水晶\",\"12\":\"量子蓝\",\"13\":\"量子绿\",\"14\":\"裁决者\",\"15\":\"感染者\",\"16\":\"月面狂袭\",\"17\":\"银河护卫\",\"18\":\"蜂刺\",\"19\":\"精英初代\",\"20\":\"精英鲨鱼\",\"21\":\"精英凤凰\",\"22\":\"精英黄蜂\",\"23\":\"精英藤蔓\",\"24\":\"精英混沌\",\"25\":\"精英光束\",\"\":0},\"title\":{\"0\":\"成群结队\",\"1\":\"会发射子弹\",\"2\":\"稍微强点\",\"3\":\"速度较快\",\"4\":\"自我毁灭\",\"5\":\"队列移动\",\"6\":\"生命较强\",\"7\":\"速度快\",\"8\":\"快速弹幕\",\"9\":\"综合实力\",\"10\":\"捉摸不透\",\"11\":\"伤害较高\",\"12\":\"散射子弹\",\"13\":\"散射强化\",\"14\":\"高速攻击波\",\"15\":\"污染物\",\"16\":\"散射光弹\",\"17\":\"乱射光弹\",\"18\":\"高速针刺\",\"19\":\"经验\",\"20\":\"鲨鱼\",\"21\":\"凤凰\",\"22\":\"黄蜂\",\"23\":\"丛林\",\"24\":\"混沌\",\"25\":\"光芒\",\"\":0},\"info\":{\"0\":\"量产飞机\\\\造价很低\\\\因此出现了大批量\",\"1\":\"改造量产机\\\\装载了一些基础武器\",\"2\":\"改造紫色机\\\\强化速度\\\\配置更强的武器和装甲\",\"3\":\"本身不会发动攻击\\\\但是撞上了就不妙了\",\"4\":\"旋转刃会瞄准对方飞机\\\\冲向前去\\\\同归于尽\",\"5\":\"来无影去无踪\\\\ 根本无法窥探到它的飞行轨迹\",\"6\":\"生命较多\\\\能力一般\\\\改造的装甲飞船\",\"7\":\"比起绿色装甲的机动性好一些\",\"8\":\"会持续发展散射子弹的飞机\\\\很危险\",\"9\":\"整体能力平均\\\\数量较多时难以对付\",\"10\":\"突然出现在你的面前\\\\简直防不胜防\",\"11\":\"会发射威力很强的贯穿弹\\\\请务必小心\",\"12\":\"发射散射子弹的飞机\\\\能力平均\",\"13\":\"量子强化版本\\\\比起蓝版要强许多\",\"14\":\"发射高速攻击的大范围子弹\\\\很难躲过去\",\"15\":\"感染腐蚀的机体\\\\飞过的地方会留下毒雾\\\\务必小心\",\"16\":\"月面飞船\\\\散射高速光弹的攻击\",\"17\":\"无规律地散射光弹\\\\守护一切的力量\",\"18\":\"快速移动\\\\并且发射针刺攻击\",\"19\":\"搭载最新技术的\\\\原型的精英机体\\\\功能用途很多\",\"20\":\"搭载最新技术的\\\\鲨鱼强化机体\\\\发射水属性子弹\",\"21\":\"搭载最新技术的\\\\凤凰强化机体\\\\发射火属性子弹\",\"22\":\"搭载最新技术的\\\\黄蜂强化机体\\\\发射雷属性子弹\",\"23\":\"搭载最新技术的\\\\藤蔓强化机体\\\\发射风属性子弹\",\"24\":\"改进的精英机体\\\\拥有非常强大的力量\",\"25\":\"超越一切精英机体的存在\\\\集合各种能力于一身\",\"\":0},\"rank\":{\"0\":\"1\",\"1\":\"1\",\"2\":\"1\",\"3\":\"1\",\"4\":\"1\",\"5\":\"1\",\"6\":\"1\",\"7\":\"1\",\"8\":\"1\",\"9\":\"1\",\"10\":\"1\",\"11\":\"1\",\"12\":\"1\",\"13\":\"1\",\"14\":\"1\",\"15\":\"1\",\"16\":\"1\",\"17\":\"1\",\"18\":\"1\",\"19\":\"2\",\"20\":\"2\",\"21\":\"2\",\"22\":\"2\",\"23\":\"2\",\"24\":\"2\",\"25\":\"2\",\"\":0},\"skinId\":{\"0\":\"0\",\"1\":\"1\",\"2\":\"2\",\"3\":\"3\",\"4\":\"4\",\"5\":\"5\",\"6\":\"6\",\"7\":\"7\",\"8\":\"8\",\"9\":\"9\",\"10\":\"10\",\"11\":\"11\",\"12\":\"12\",\"13\":\"13\",\"14\":\"14\",\"15\":\"15\",\"16\":\"16\",\"17\":\"17\",\"18\":\"18\",\"19\":\"19\",\"20\":\"20\",\"21\":\"21\",\"22\":\"22\",\"23\":\"23\",\"24\":\"24\",\"25\":\"25\",\"\":0},\"AIMode\":{\"0\":\"0\",\"1\":\"0\",\"2\":\"0\",\"3\":\"0\",\"4\":\"3\",\"5\":\"4\",\"6\":\"0\",\"7\":\"0\",\"8\":\"0\",\"9\":\"3\",\"10\":\"4\",\"11\":\"1\",\"12\":\"1\",\"13\":\"1\",\"14\":\"0\",\"15\":\"0\",\"16\":\"0\",\"17\":\"0\",\"18\":\"2\",\"19\":\"5\",\"20\":\"5\",\"21\":\"5\",\"22\":\"5\",\"23\":\"5\",\"24\":\"5\",\"25\":\"5\",\"\":0},\"hp\":{\"0\":\"1\",\"1\":\"2\",\"2\":\"4\",\"3\":\"6\",\"4\":\"6\",\"5\":\"8\",\"6\":\"12\",\"7\":\"5\",\"8\":\"8\",\"9\":\"5\",\"10\":\"10\",\"11\":\"20\",\"12\":\"10\",\"13\":\"20\",\"14\":\"6\",\"15\":\"10\",\"16\":\"14\",\"17\":\"12\",\"18\":\"12\",\"19\":\"24\",\"20\":\"30\",\"21\":\"34\",\"22\":\"40\",\"23\":\"45\",\"24\":\"52\",\"25\":\"60\",\"\":0},\"atk\":{\"0\":\"0\",\"1\":\"50\",\"2\":\"30\",\"3\":\"40\",\"4\":\"20\",\"5\":\"10\",\"6\":\"10\",\"7\":\"10\",\"8\":\"10\",\"9\":\"10\",\"10\":\"10\",\"11\":\"50\",\"12\":\"20\",\"13\":\"40\",\"14\":\"10\",\"15\":\"100\",\"16\":\"20\",\"17\":\"20\",\"18\":\"20\",\"19\":\"20\",\"20\":\"20\",\"21\":\"100\",\"22\":\"30\",\"23\":\"30\",\"24\":\"100\",\"25\":\"100\",\"\":0},\"moveSpeed\":{\"0\":\"20\",\"1\":\"10\",\"2\":\"20\",\"3\":\"75\",\"4\":\"10\",\"5\":\"50\",\"6\":\"10\",\"7\":\"10\",\"8\":\"10\",\"9\":\"10\",\"10\":\"100\",\"11\":\"50\",\"12\":\"20\",\"13\":\"40\",\"14\":\"40\",\"15\":\"50\",\"16\":\"10\",\"17\":\"10\",\"18\":\"30\",\"19\":\"10\",\"20\":\"50\",\"21\":\"50\",\"22\":\"30\",\"23\":\"30\",\"24\":\"40\",\"25\":\"100\",\"\":0},\"shootSpeed\":{\"0\":\"1\",\"1\":\"0.6\",\"2\":\"0.8\",\"3\":\"1\",\"4\":\"1\",\"5\":\"0.5\",\"6\":\"1\",\"7\":\"1\",\"8\":\"0.2\",\"9\":\"1\",\"10\":\"0.5\",\"11\":\"0.5\",\"12\":\"0.2\",\"13\":\"0.2\",\"14\":\"0.5\",\"15\":\"1\",\"16\":\"0.3\",\"17\":\"0.4\",\"18\":\"0.2\",\"19\":\"0.5\",\"20\":\"0.5\",\"21\":\"0.7\",\"22\":\"0.4\",\"23\":\"1\",\"24\":\"0.1\",\"25\":\"0.4\",\"\":0},\"bulletId\":{\"0\":\"49\",\"1\":\"50\",\"2\":\"51\",\"3\":\"52\",\"4\":\"53\",\"5\":\"54\",\"6\":\"55\",\"7\":\"56\",\"8\":\"57\",\"9\":\"58\",\"10\":\"59\",\"11\":\"60\",\"12\":\"61\",\"13\":\"62\",\"14\":\"63\",\"15\":\"64\",\"16\":\"65\",\"17\":\"66\",\"18\":\"67\",\"19\":\"68\",\"20\":\"69\",\"21\":\"70\",\"22\":\"71\",\"23\":\"72\",\"24\":\"73\",\"25\":\"74\",\"\":0},\"danger\":{\"0\":\"0\",\"1\":\"0\",\"2\":\"0\",\"3\":\"0.5\",\"4\":\"0.5\",\"5\":\"0.8\",\"6\":\"1.2\",\"7\":\"1.2\",\"8\":\"2\",\"9\":\"2\",\"10\":\"3\",\"11\":\"3\",\"12\":\"3.5\",\"13\":\"3.5\",\"14\":\"4\",\"15\":\"3.2\",\"16\":\"5\",\"17\":\"5\",\"18\":\"4.5\",\"19\":\"0.5\",\"20\":\"1.8\",\"21\":\"2.2\",\"22\":\"3.2\",\"23\":\"4.2\",\"24\":\"5.2\",\"25\":\"5.6\",\"\":0},\"group\":{\"0\":\"base\",\"1\":\"base\",\"2\":\"base\",\"3\":\"base\",\"4\":\"base\",\"5\":\"base\",\"6\":\"base\",\"7\":\"base\",\"8\":\"base\",\"9\":\"base\",\"10\":\"base\",\"11\":\"base\",\"12\":\"base\",\"13\":\"base\",\"14\":\"base\",\"15\":\"base\",\"16\":\"base\",\"17\":\"base\",\"18\":\"base\",\"19\":\"elite\",\"20\":\"elite\",\"21\":\"elite\",\"22\":\"elite\",\"23\":\"elite\",\"24\":\"elite\",\"25\":\"elite\",\"\":0},\"\":{\"0\":\"\",\"1\":\"\",\"2\":\"\",\"3\":\"\",\"4\":\"\",\"5\":\"\",\"6\":\"\",\"7\":\"\",\"8\":\"\",\"9\":\"\",\"10\":\"\",\"11\":\"\",\"12\":\"\",\"13\":\"\",\"14\":\"\",\"15\":\"\",\"16\":\"\",\"17\":\"\",\"18\":\"\",\"19\":\"\",\"20\":\"\",\"21\":\"\",\"22\":\"\",\"23\":\"\",\"24\":\"\",\"25\":\"\",\"\":0}},\"keys\":[\"name\",\"title\",\"info\",\"rank\",\"skinId\",\"AIMode\",\"hp\",\"atk\",\"moveSpeed\",\"shootSpeed\",\"bulletId\",\"danger\",\"group\",\"\"],\"items\":[\"0\",\"1\",\"2\",\"3\",\"4\",\"5\",\"6\",\"7\",\"8\",\"9\",\"10\",\"11\",\"12\",\"13\",\"14\",\"15\",\"16\",\"17\",\"18\",\"19\",\"20\",\"21\",\"22\",\"23\",\"24\",\"25\",\"\"]}","event":"{\"table\":{\"name\":{\"0\":\"新的装备\",\"1\":\"新的技能\",\"2\":\"飞船出售\",\"3\":\"来历不明\",\"4\":\"新的技能\",\"5\":\"交换装备\",\"6\":\"能量不足\",\"7\":\"备用能源\",\"8\":\"来历不明\",\"9\":\"发现矿物\",\"10\":\"发现能源\",\"\":0},\"title\":{\"0\":\"有一艘飞船向你提出交易请求\\\\希望卖出他们的装备。你同意吗?\",\"1\":\"有一艘飞船向你提出交易请求\\\\希望卖出他们的技能。你同意吗? \",\"2\":\"你来到了飞船的建造基地\\\\这里能购买他们秘密研究的飞船。你同意吗?\",\"3\":\"来历不明的飞船向你发送了信息\\\\他希望你借给他们一些资金用于修复飞船。如果同意他们会提供一些报酬。\",\"4\":\"能源交易\\\\有一艘飞船提出了交易请求\\\\希望卖出他们的能量。 \",\"5\":\"发现了星球上的交易所\\\\可以用能量换取一些装备。\",\"6\":\"发现了星球上的交易所\\\\可以用能量交换一个技能\",\"7\":\"你遇到了一艘飞船\\\\他们打算储备一些能源\\\\你原意支付能源 换取一些金币吗?\",\"8\":\"来历不明的飞船向你发送了信息\\\\他们的能源不足了\\\\想向你借一些能源。如果同意\\\\他们可能会给你一些报酬。\",\"9\":\"你发现了某个星球上的金属矿物\\\\开采后将获得一些金币。\",\"10\":\"你发现了某个星球上有能源矿石\\\\开采后可以获得能源。\",\"\":0},\"costItem\":{\"0\":\"gold\",\"1\":\"gold\",\"2\":\"gold\",\"3\":\"gold\",\"4\":\"gold\",\"5\":\"energy\",\"6\":\"energy\",\"7\":\"energy\",\"8\":\"energy\",\"9\":\"none\",\"10\":\"none\",\"\":0},\"getItem\":{\"0\":\"equip\",\"1\":\"skill\",\"2\":\"plane\",\"3\":\"random\",\"4\":\"energy\",\"5\":\"equip\",\"6\":\"skill\",\"7\":\"gold\",\"8\":\"random\",\"9\":\"gold\",\"10\":\"energy\",\"\":0},\"rateValue\":{\"0\":\"20\",\"1\":\"25\",\"2\":\"20\",\"3\":\"10\",\"4\":\"50\",\"5\":\"10\",\"6\":\"5\",\"7\":\"10\",\"8\":\"10\",\"9\":\"5\",\"10\":\"30\",\"\":0}},\"keys\":[\"name\",\"title\",\"costItem\",\"getItem\",\"rateValue\"],\"items\":[\"0\",\"1\",\"2\",\"3\",\"4\",\"5\",\"6\",\"7\",\"8\",\"9\",\"10\",\"\"]}","skill":"{\"table\":{\"name\":{\"0\":\"量子纠缠\",\"1\":\"导弹发射\",\"2\":\"超星冲击\",\"3\":\"子弹干扰器\",\"4\":\"奇点\",\"5\":\"复制品\",\"6\":\"雷球\",\"7\":\"完全恢复\",\"8\":\"重塑\",\"9\":\"逃离星球\",\"10\":\"挥金如土\",\"11\":\"危险炸弹\",\"12\":\"金钱乱数\",\"13\":\"火焰扩散\",\"14\":\"敌人削弱\",\"15\":\"弹幕清除\",\"16\":\"全军突击\",\"17\":\"能量转化\",\"18\":\"能量毁灭\",\"19\":\"持续恢复\",\"\":0},\"title\":{\"0\":\"减速器\",\"1\":\"导弹\",\"2\":\"发射星星\",\"3\":\"干扰子弹\",\"4\":\"消除子弹\",\"5\":\"复制\",\"6\":\"持续伤害\",\"7\":\"修复机体\",\"8\":\"销毁重抽\",\"9\":\"逃离危险\",\"10\":\"金钱力量\",\"11\":\"炸弹攻击\",\"12\":\"博弈\",\"13\":\"随机火焰\",\"14\":\"HP削减\",\"15\":\"消除弹幕\",\"16\":\"齿轮\",\"17\":\"子弹变能量\",\"18\":\"消耗能量\",\"19\":\"每秒恢复\",\"\":0},\"info\":{\"0\":\"使用后屏幕上的全部弹幕速度都将减半。\",\"1\":\"持续发射导弹扩散攻击\",\"2\":\"持续散射星星的必杀技\",\"3\":\"干扰普通子弹的运动轨迹。(随机切换角度)\",\"4\":\"召唤一个能吸收敌人子弹的魔法阵。\",\"5\":\"随机复制队伍中的一架飞机\\\\并添加到队伍。\",\"6\":\"召唤雷电球从天而降。\",\"7\":\"恢复全部机体的生命值\",\"8\":\"随机毁掉一架飞机\\\\并且重新获得一架。\",\"9\":\"跳过该星球的探索过程\\\\直接进入最终BOSS区域\",\"10\":\"消耗1000金币发射强力攻击\\\\金币不足时次数降低\",\"11\":\"释放大量炸弹\\\\敌人碰到后会发生大爆炸\",\"12\":\"重列排列你获得金钱的数字\",\"13\":\"随机在屏幕上产生火焰环\\\\扩散攻击\",\"14\":\"削减场上所有飞机的生命值一半(Boss除外)\",\"15\":\"5秒内\\\\每秒清除一次屏幕上的敌方弹幕\",\"16\":\"场上的每一架飞机都会发射几次齿轮攻击\",\"17\":\"将场上所有敌方的子弹都转变为能量\",\"18\":\"自动摧毁场上一架敌机\\\\每架消耗3能量\\\\能力不足时中断\",\"19\":\"每秒为每个飞机恢复HP30%\\\\一共恢复10秒\",\"\":0},\"rateValue\":{\"0\":\"80\",\"1\":\"80\",\"2\":\"80\",\"3\":\"40\",\"4\":\"30\",\"5\":\"30\",\"6\":\"10\",\"7\":\"10\",\"8\":\"50\",\"9\":\"2\",\"10\":\"50\",\"11\":\"20\",\"12\":\"10\",\"13\":\"100\",\"14\":\"50\",\"15\":\"50\",\"16\":\"50\",\"17\":\"25\",\"18\":\"10\",\"19\":\"20\",\"\":0},\"gold\":{\"0\":\"600\",\"1\":\"1000\",\"2\":\"800\",\"3\":\"600\",\"4\":\"900\",\"5\":\"3000\",\"6\":\"900\",\"7\":\"1200\",\"8\":\"2500\",\"9\":\"800\",\"10\":\"666\",\"11\":\"1500\",\"12\":\"2000\",\"13\":\"1000\",\"14\":\"1000\",\"15\":\"800\",\"16\":\"1200\",\"17\":\"1000\",\"18\":\"850\",\"19\":\"2400\",\"\":0},\"group\":{\"0\":\"init\",\"1\":\"init\",\"2\":\"init\",\"3\":\"init\",\"4\":\"\",\"5\":\"\",\"6\":\"\",\"7\":\"\",\"8\":\"\",\"9\":\"\",\"10\":\"\",\"11\":\"\",\"12\":\"\",\"13\":\"\",\"14\":\"\",\"15\":\"\",\"16\":\"\",\"17\":\"\",\"18\":\"\",\"19\":\"\",\"\":0},\"\":{\"0\":\"*\",\"1\":\"*\",\"2\":\"*\",\"3\":\"*\",\"4\":\"*\",\"5\":\"*\",\"6\":\"*\",\"7\":\"*\",\"8\":\"*\",\"9\":\"*\",\"10\":\"*\",\"11\":\"*\",\"12\":\"*\",\"13\":\"*\",\"14\":\"*\",\"15\":\"*\",\"16\":\"*\",\"17\":\"*\",\"18\":\"*\",\"19\":\"*\",\"\":0}},\"keys\":[\"name\",\"title\",\"info\",\"rateValue\",\"gold\",\"group\",\"\"],\"items\":[\"0\",\"1\",\"2\",\"3\",\"4\",\"5\",\"6\",\"7\",\"8\",\"9\",\"10\",\"11\",\"12\",\"13\",\"14\",\"15\",\"16\",\"17\",\"18\",\"19\",\"\"]}","equip":"{\"table\":{\"name\":{\"0\":\"生命芯片I\",\"1\":\"生命芯片II\",\"2\":\"生命芯片III\",\"3\":\"强化子弹I\",\"4\":\"强化子弹II\",\"5\":\"强化子弹III\",\"6\":\"射速芯片I\",\"7\":\"射速芯片II\",\"8\":\"射速芯片III\",\"9\":\"移动芯片I\",\"10\":\"移动芯片II\",\"11\":\"移动芯片III\",\"12\":\"人多力量大\",\"13\":\"一币通关\",\"14\":\"自动修复\",\"15\":\"生命合成器\",\"16\":\"金币回收器\",\"17\":\"外星居住证\",\"18\":\"领航仪器\",\"19\":\"暴击器\",\"20\":\"乱射器\",\"21\":\"飞机探索箱\",\"22\":\"道具探索箱\",\"23\":\"金币复制器\",\"24\":\"能量增幅器\",\"25\":\"商人手段\",\"26\":\"恢复芯片科技\",\"27\":\"资源回收\",\"28\":\"伤害监测仪\",\"29\":\"危险探测仪\",\"30\":\"生命检测仪\",\"31\":\"散弹追加I\",\"32\":\"散弹追加II\",\"33\":\"矿物开采器\",\"34\":\"金币开采器\",\"35\":\"自动指挥\",\"36\":\"病毒\",\"37\":\"事件预警芯片\",\"38\":\"商人联盟芯片\",\"39\":\"危险增幅\",\"40\":\"节能模式\",\"41\":\"交易专家\",\"42\":\"硬直降低\",\"43\":\"硬直取消\",\"44\":\"敌人缩小\",\"45\":\"时间齿轮加速\",\"46\":\"时间齿轮减速\",\"47\":\"超级科技分析仪器\",\"48\":\"领主风范\",\"49\":\"对BOSS战芯片\",\"50\":\"双子座芯片\",\"51\":\"群体战术\",\"52\":\"流程加速\",\"53\":\"危险扳机\",\"54\":\"绝对公正\",\"55\":\"死亡流星\",\"56\":\"死亡清空\",\"57\":\"牺牲精神\",\"58\":\"陷阱延迟\",\"59\":\"子弹缩小\",\"\":0},\"title\":{\"0\":\"最大生命\",\"1\":\"最大生命\",\"2\":\"最大生命\",\"3\":\"子弹威力\",\"4\":\"子弹威力\",\"5\":\"子弹威力\",\"6\":\"子弹射速\",\"7\":\"子弹射速\",\"8\":\"子弹射速\",\"9\":\"移动速度\",\"10\":\"移动速度\",\"11\":\"移动速度\",\"12\":\"越多越好\",\"13\":\"单打独斗\",\"14\":\"急救\",\"15\":\"概率增加\",\"16\":\"概率增加\",\"17\":\"额外行星币\",\"18\":\"增加机位\",\"19\":\"概率暴击\",\"20\":\"散乱射击\",\"21\":\"新的飞机\",\"22\":\"新的道具\",\"23\":\"更多金钱\",\"24\":\"更多能量\",\"25\":\"更多折扣\",\"26\":\"更多恢复\",\"27\":\"重复利用\",\"28\":\"检测伤害\",\"29\":\"检测危险\",\"30\":\"检测生命\",\"31\":\"增加数量\",\"32\":\"增加数量\",\"33\":\"能量概率\",\"34\":\"金矿概率\",\"35\":\"自动队列\",\"36\":\"无法删除\",\"37\":\"事件\",\"38\":\"商店\",\"39\":\"更困难\",\"40\":\"更少能量\",\"41\":\"更便宜\",\"42\":\"硬直降低\",\"43\":\"硬直取消\",\"44\":\"变小\",\"45\":\"时间\",\"46\":\"时间\",\"47\":\"三合一芯片\",\"48\":\"领导者\",\"49\":\"弱化BOSS\",\"50\":\"双重精英\",\"51\":\"敌人数量\",\"52\":\"节约时间\",\"53\":\"危机\",\"54\":\"1HP\",\"55\":\"流星\",\"56\":\"清屏\",\"57\":\"恢复\",\"58\":\"延迟\",\"59\":\"缩小化\",\"\":0},\"info\":{\"0\":\"增加飞船的生命上限10%\",\"1\":\"增加飞船的生命上限30%\",\"2\":\"增加飞船的生命上限50%\",\"3\":\"增加全体飞船子弹威力10%\",\"4\":\"增加全体飞船子弹威力30%\",\"5\":\"增加全体飞船子弹威力50%\",\"6\":\"全体飞机子弹发射速度提高10%\",\"7\":\"全体飞机子弹发射速度提高30%\",\"8\":\"全体飞机子弹发射速度提高50%\",\"9\":\"全体飞机子弹移动速度提高10%\",\"10\":\"全体飞机子弹移动速度提高30%\",\"11\":\"全体飞机子弹移动速度提高50%\",\"12\":\"拥有的飞机越多\\\\全体飞机能力越强\\\\每架飞机增加5%的属性\",\"13\":\"只拥有一架飞机时\\\\飞机的所有能力增加200%\",\"14\":\"当飞船体力低时会自动恢复\",\"15\":\"增加敌人掉落的生命概率\",\"16\":\"增加敌人掉落金币的概率\",\"17\":\"BOSS掉落的行星币 50%概率会多掉落两个\",\"18\":\"增加飞机位置1个\",\"19\":\"飞机暴击概率变大\\\\暴击时发射双倍威力的子弹\",\"20\":\"所有线性子弹的发射方向将会变的不稳定\",\"21\":\"击败敌人更容易掉落箱子\",\"22\":\"击败敌人更容易掉落道具\",\"23\":\"获得金币时 额外获得一个金币\",\"24\":\"获得能量时 额外获得一个能量\",\"25\":\"在商店 购买东西时 更容易出现折扣\",\"26\":\"掉落的恢复道具时额外掉落3个\",\"27\":\"损坏的飞机会掉落金币\\\\一定概率\",\"28\":\"获得装备后\\\\自己或敌人受到攻击都会显示子弹的伤害值\",\"29\":\"能预知敌人的危险行动 (未生效)\",\"30\":\"装备后 新出现的敌人会 显示生命值条。\",\"31\":\"增加所有飞机的散弹的 数量 1个\",\"32\":\"增加所有飞机的散弹的 数量 2个\",\"33\":\"休息区更容易出现能量矿石\",\"34\":\"休息区更容易出现金矿石\",\"35\":\"队列进行自动的随机切换\",\"36\":\"无法主动删除装备技能 和 飞船\",\"37\":\"休息区更容易出现 特殊的事件\",\"38\":\"休息区更容易出现 商店\",\"39\":\"探索出现的星球 基础危险度大幅提升\",\"40\":\"探索星球的基本能量消费降低\",\"41\":\"出现事件交易时 消耗的资源 减少50%\",\"42\":\"被子弹击中后飞机失控时间降低50%\",\"43\":\"被子弹击中后飞机不会再陷入短暂的失控状态\",\"44\":\"敌人的体积变小(子弹并不会变小)\",\"45\":\"周围的时间发生了改变\\\\自身以外的东西都变快了一些\",\"46\":\"周围的时间发生了改变\\\\自身以外的东西都变慢了一些\",\"47\":\"同时具有 伤害监测仪\\\\危险探测仪\\\\生命检测仪 的效果\",\"48\":\"休息区更容易出现特殊事件\\\\商店和矿石\",\"49\":\"持有该芯片时\\\\BOSS开局便降低到半血状态\",\"50\":\"如果持有该芯片\\\\会同时出现两个精英飞船\",\"51\":\"每波产生的敌人追加出现5个\",\"52\":\"星球旅行所消耗的时间缩短一半\",\"53\":\"飞机生命低于25%时\\\\子弹威力提高100%\",\"54\":\"自己飞机和敌人飞机都是1击被破坏\\\\(对BOSS时造成5倍伤害)\",\"55\":\"当拥有的飞机被摧毁时\\\\立即发动 流星的必杀技能\",\"56\":\"当拥有的飞机被摧毁时\\\\立即发动 清除全屏弹幕的必杀技\",\"57\":\"当拥有的飞机被摧毁时\\\\立即发动 完全恢复其他飞机的生命值\",\"58\":\"不那么容易再出现机关陷阱\\\\至少延迟1分钟后才会出现一次\",\"59\":\"敌方杂兵发射的子弹\\\\体积全部缩小30%\",\"\":0},\"rateValue\":{\"0\":\"55\",\"1\":\"20\",\"2\":\"10\",\"3\":\"50\",\"4\":\"20\",\"5\":\"10\",\"6\":\"45\",\"7\":\"20\",\"8\":\"10\",\"9\":\"45\",\"10\":\"20\",\"11\":\"10\",\"12\":\"8\",\"13\":\"5\",\"14\":\"5\",\"15\":\"10\",\"16\":\"5\",\"17\":\"5\",\"18\":\"5\",\"19\":\"5\",\"20\":\"10\",\"21\":\"10\",\"22\":\"10\",\"23\":\"10\",\"24\":\"10\",\"25\":\"8\",\"26\":\"8\",\"27\":\"8\",\"28\":\"10\",\"29\":\"10\",\"30\":\"10\",\"31\":\"8\",\"32\":\"5\",\"33\":\"15\",\"34\":\"15\",\"35\":\"10\",\"36\":\"3\",\"37\":\"16\",\"38\":\"14\",\"39\":\"8\",\"40\":\"9\",\"41\":\"10\",\"42\":\"5\",\"43\":\"4\",\"44\":\"5\",\"45\":\"1\",\"46\":\"1\",\"47\":\"5\",\"48\":\"14\",\"49\":\"10\",\"50\":\"5\",\"51\":\"4\",\"52\":\"1\",\"53\":\"4\",\"54\":\"4\",\"55\":\"5\",\"56\":\"5\",\"57\":\"5\",\"58\":\"10\",\"59\":\"10\",\"\":0},\"gold\":{\"0\":\"50\",\"1\":\"250\",\"2\":\"1250\",\"3\":\"50\",\"4\":\"250\",\"5\":\"1250\",\"6\":\"50\",\"7\":\"500\",\"8\":\"1500\",\"9\":\"100\",\"10\":\"400\",\"11\":\"800\",\"12\":\"1500\",\"13\":\"1500\",\"14\":\"1500\",\"15\":\"250\",\"16\":\"300\",\"17\":\"2000\",\"18\":\"1000\",\"19\":\"600\",\"20\":\"400\",\"21\":\"1200\",\"22\":\"1500\",\"23\":\"900\",\"24\":\"1200\",\"25\":\"1000\",\"26\":\"500\",\"27\":\"250\",\"28\":\"250\",\"29\":\"300\",\"30\":\"400\",\"31\":\"400\",\"32\":\"600\",\"33\":\"240\",\"34\":\"240\",\"35\":\"300\",\"36\":\"999\",\"37\":\"650\",\"38\":\"650\",\"39\":\"450\",\"40\":\"680\",\"41\":\"1400\",\"42\":\"1800\",\"43\":\"2200\",\"44\":\"1250\",\"45\":\"2000\",\"46\":\"2000\",\"47\":\"2800\",\"48\":\"4200\",\"49\":\"4800\",\"50\":\"2500\",\"51\":\"2500\",\"52\":\"3800\",\"53\":\"3000\",\"54\":\"5000\",\"55\":\"3500\",\"56\":\"3500\",\"57\":\"3500\",\"58\":\"2000\",\"59\":\"2500\",\"\":0},\"group\":{\"0\":\"init\",\"1\":\"init\",\"2\":\"\",\"3\":\"init\",\"4\":\"init\",\"5\":\"\",\"6\":\"init\",\"7\":\"init\",\"8\":\"\",\"9\":\"init\",\"10\":\"init\",\"11\":\"\",\"12\":\"\",\"13\":\"\",\"14\":\"\",\"15\":\"init\",\"16\":\"init\",\"17\":\"\",\"18\":\"init\",\"19\":\"\",\"20\":\"\",\"21\":\"\",\"22\":\"\",\"23\":\"\",\"24\":\"\",\"25\":\"\",\"26\":\"\",\"27\":\"\",\"28\":\"\",\"29\":\"\",\"30\":\"\",\"31\":\"\",\"32\":\"\",\"33\":\"\",\"34\":\"\",\"35\":\"\",\"36\":\"\",\"37\":\"\",\"38\":\"\",\"39\":\"\",\"40\":\"\",\"41\":\"\",\"42\":\"\",\"43\":\"\",\"44\":\"\",\"45\":\"\",\"46\":\"\",\"47\":\"character\",\"48\":\"character\",\"49\":\"character\",\"50\":\"\",\"51\":\"\",\"52\":\"\",\"53\":\"\",\"54\":\"\",\"55\":\"\",\"56\":\"\",\"57\":\"\",\"58\":\"\",\"59\":\"\",\"\":0},\"buffName\":{\"0\":\"add_hp\",\"1\":\"add_hp\",\"2\":\"add_hp\",\"3\":\"add_dmg\",\"4\":\"add_dmg\",\"5\":\"add_dmg\",\"6\":\"add_spd\",\"7\":\"add_spd\",\"8\":\"add_spd\",\"9\":\"add_mov\",\"10\":\"add_mov\",\"11\":\"add_mov\",\"12\":\"FUNCTION\",\"13\":\"FUNCTION\",\"14\":\"auto_heal\",\"15\":\"hp_drop_rate\",\"16\":\"gold_drop_rate\",\"17\":\"gem_drop_rate\",\"18\":\"add_lead\",\"19\":\"lucky_shoot_rate\",\"20\":\"line_shoot_random\",\"21\":\"chest_drop_rate\",\"22\":\"item_drop_rate\",\"23\":\"ext_get_gold\",\"24\":\"ext_get_energy\",\"25\":\"shop_off_rate\",\"26\":\"ext_get_heal\",\"27\":\"myplane_recycle\",\"28\":\"gui_damage_show\",\"29\":\"gui_danger_check\",\"30\":\"gui_hpbar_show\",\"31\":\"scope_shoot_add\",\"32\":\"scope_shoot_add\",\"33\":\"map_energy_rate\",\"34\":\"map_gold_rate\",\"35\":\"queue_break\",\"36\":\"item_delete_lock\",\"37\":\"map_event_rate\",\"38\":\"map_shop_rate\",\"39\":\"planet_danger_increase\",\"40\":\"planet_cost\",\"41\":\"event_off_max\",\"42\":\"shake_time_down\",\"43\":\"shake_time_down\",\"44\":\"enemy_size\",\"45\":\"game_speed\",\"46\":\"game_speed\",\"47\":\"FUNCTION\",\"48\":\"FUNCTION\",\"49\":\"boss_hp_decrease\",\"50\":\"create_elite_double\",\"51\":\"create_more_enemy\",\"52\":\"travel_distance_double\",\"53\":\"danger_trigger\",\"54\":\"all_one_kill\",\"55\":\"death_skill_use\",\"56\":\"death_skill_use\",\"57\":\"death_skill_use\",\"58\":\"break_danger_switch\",\"59\":\"enemy_bullet_size\",\"\":0},\"buffValue\":{\"0\":\"10\",\"1\":\"30\",\"2\":\"50\",\"3\":\"10\",\"4\":\"30\",\"5\":\"50\",\"6\":\"10\",\"7\":\"30\",\"8\":\"50\",\"9\":\"10\",\"10\":\"30\",\"11\":\"50\",\"12\":\"morePlanePower\",\"13\":\"lessPlanePower\",\"14\":\"1\",\"15\":\"30\",\"16\":\"30\",\"17\":\"50\",\"18\":\"10\",\"19\":\"25\",\"20\":\"10\",\"21\":\"20\",\"22\":\"20\",\"23\":\"1\",\"24\":\"1\",\"25\":\"50\",\"26\":\"3\",\"27\":\"1\",\"28\":\"1\",\"29\":\"1\",\"30\":\"1\",\"31\":\"1\",\"32\":\"1\",\"33\":\"50\",\"34\":\"50\",\"35\":\"1\",\"36\":\"1\",\"37\":\"50\",\"38\":\"50\",\"39\":\"50\",\"40\":\"50\",\"41\":\"50\",\"42\":\"50\",\"43\":\"95\",\"44\":\"-50\",\"45\":\"30\",\"46\":\"-30\",\"47\":\"superGameInfo\",\"48\":\"leadStyle\",\"49\":\"50\",\"50\":\"1\",\"51\":\"5\",\"52\":\"1\",\"53\":\"1\",\"54\":\"1\",\"55\":\"2\",\"56\":\"15\",\"57\":\"7\",\"58\":\"30\",\"59\":\"-30\",\"\":0}},\"keys\":[\"name\",\"title\",\"info\",\"rateValue\",\"gold\",\"group\",\"buffName\",\"buffValue\"],\"items\":[\"0\",\"1\",\"2\",\"3\",\"4\",\"5\",\"6\",\"7\",\"8\",\"9\",\"10\",\"11\",\"12\",\"13\",\"14\",\"15\",\"16\",\"17\",\"18\",\"19\",\"20\",\"21\",\"22\",\"23\",\"24\",\"25\",\"26\",\"27\",\"28\",\"29\",\"30\",\"31\",\"32\",\"33\",\"34\",\"35\",\"36\",\"37\",\"38\",\"39\",\"40\",\"41\",\"42\",\"43\",\"44\",\"45\",\"46\",\"47\",\"48\",\"49\",\"50\",\"51\",\"52\",\"53\",\"54\",\"55\",\"56\",\"57\",\"58\",\"59\",\"\"]}","player":"{\"table\":{\"name\":{\"0\":\"4399漫游冒险家\",\"1\":\"4399太空盗贼\",\"2\":\"4399星盟成员\",\"3\":\"4399独行者\",\"4\":\"4399机器人\",\"5\":\"4399神秘人\",\"6\":\"4399时空旅行者\",\"7\":\"4399星际领主\",\"40\":\"\",\"41\":\"\",\"42\":\"\",\"43\":\"\",\"44\":\"\",\"45\":\"\",\"46\":\"\",\"47\":\"\",\"48\":\"\",\"49\":\"\",\"50\":\"\",\"51\":\"\",\"52\":\"\",\"\":0},\"info\":{\"0\":\"经验丰富\\\\在太空中探索的冒险家。能力平均\\\\拥有很多奇妙的装备。\\\\初始拥有100点能量。\",\"1\":\"经常在太空中打劫其他飞船的组织。幸运值很高\\\\拥有增加金钱的道具。初始的时候就有1000金币。\",\"2\":\"现星系联盟的核心成员\\\\为了寻找组织的飞船残骸\\\\找到事情的真相而前行\\\\擅长高射速度武器。\",\"3\":\"孤独的人\\\\独自一人在太空中漫无目的游荡。只能控制2架飞机\\\\但是可以大幅强化飞船攻击力。\",\"4\":\"自主思考能力的机器人\\\\对飞船的操控能力非常好。携带的芯片能够让你清楚观察敌人的状态。\",\"5\":\"未知身份的星级旅行者\\\\总是带着帽子\\\\没有人知道他的身世(特殊人物\\\\能力加成低\\\\无装备技能)\",\"6\":\"为了某个目的而穿越时空\\\\来到这个星系探索的旅人\\\\开局时随机获取几个飞船和道具。\",\"7\":\"统领某个星系的领导者\\\\能够增幅飞船的全部能力。\",\"40\":\"\",\"41\":\"\",\"42\":\"\",\"43\":\"\",\"44\":\"\",\"45\":\"\",\"46\":\"\",\"47\":\"\",\"48\":\"\",\"49\":\"\",\"50\":\"\",\"51\":\"\",\"52\":\"\",\"\":0},\"condition\":{\"0\":\"初次进入游戏解锁\",\"1\":\"游戏中累计收集99999金币解锁\",\"2\":\"到达LV.7级别解锁 \",\"3\":\"通关任意模式10次解锁\",\"4\":\"游戏中累计搜集9999能量解锁\",\"5\":\"通关普通模式解锁\",\"6\":\"通关困难模式解锁\",\"7\":\"达到LV.14 级别解锁\",\"40\":\"\",\"41\":\"\",\"42\":\"\",\"43\":\"\",\"44\":\"\",\"45\":\"\",\"46\":\"\",\"47\":\"\",\"48\":\"\",\"49\":\"\",\"50\":\"\",\"51\":\"\",\"52\":\"\",\"\":0},\"hp\":{\"0\":\"5\",\"1\":\"1\",\"2\":\"0\",\"3\":\"9\",\"4\":\"0\",\"5\":\"1\",\"6\":\"4\",\"7\":\"8\",\"40\":\"\",\"41\":\"\",\"42\":\"\",\"43\":\"\",\"44\":\"\",\"45\":\"\",\"46\":\"\",\"47\":\"\",\"48\":\"\",\"49\":\"\",\"50\":\"\",\"51\":\"\",\"52\":\"\",\"\":0},\"lead\":{\"0\":\"5\",\"1\":\"3\",\"2\":\"4\",\"3\":\"2\",\"4\":\"10\",\"5\":\"3\",\"6\":\"5\",\"7\":\"8\",\"40\":\"\",\"41\":\"\",\"42\":\"\",\"43\":\"\",\"44\":\"\",\"45\":\"\",\"46\":\"\",\"47\":\"\",\"48\":\"\",\"49\":\"\",\"50\":\"\",\"51\":\"\",\"52\":\"\",\"\":0},\"spd\":{\"0\":\"3\",\"1\":\"4\",\"2\":\"9\",\"3\":\"5\",\"4\":\"5\",\"5\":\"1\",\"6\":\"3\",\"7\":\"8\",\"40\":\"\",\"41\":\"\",\"42\":\"\",\"43\":\"\",\"44\":\"\",\"45\":\"\",\"46\":\"\",\"47\":\"\",\"48\":\"\",\"49\":\"\",\"50\":\"\",\"51\":\"\",\"52\":\"\",\"\":0},\"dmg\":{\"0\":\"2\",\"1\":\"1\",\"2\":\"3\",\"3\":\"9\",\"4\":\"3\",\"5\":\"1\",\"6\":\"3\",\"7\":\"8\",\"40\":\"\",\"41\":\"\",\"42\":\"\",\"43\":\"\",\"44\":\"\",\"45\":\"\",\"46\":\"\",\"47\":\"\",\"48\":\"\",\"49\":\"\",\"50\":\"\",\"51\":\"\",\"52\":\"\",\"\":0},\"mov\":{\"0\":\"1\",\"1\":\"4\",\"2\":\"4\",\"3\":\"5\",\"4\":\"1\",\"5\":\"1\",\"6\":\"3\",\"7\":\"8\",\"40\":\"\",\"41\":\"\",\"42\":\"\",\"43\":\"\",\"44\":\"\",\"45\":\"\",\"46\":\"\",\"47\":\"\",\"48\":\"\",\"49\":\"\",\"50\":\"\",\"51\":\"\",\"52\":\"\",\"\":0},\"luc\":{\"0\":\"2\",\"1\":\"8\",\"2\":\"2\",\"3\":\"1\",\"4\":\"1\",\"5\":\"1\",\"6\":\"3\",\"7\":\"8\",\"40\":\"\",\"41\":\"\",\"42\":\"\",\"43\":\"\",\"44\":\"\",\"45\":\"\",\"46\":\"\",\"47\":\"\",\"48\":\"\",\"49\":\"\",\"50\":\"\",\"51\":\"\",\"52\":\"\",\"\":0},\"average\":{\"0\":\"3\",\"1\":\"3.5\",\"2\":\"3.66666666667\",\"3\":\"5.16666666667\",\"4\":\"3.33333333333\",\"5\":\"1.33333333333\",\"6\":\"3.5\",\"7\":\"8\",\"40\":\"\",\"41\":\"\",\"42\":\"\",\"43\":\"\",\"44\":\"\",\"45\":\"\",\"46\":\"\",\"47\":\"\",\"48\":\"\",\"49\":\"\",\"50\":\"\",\"51\":\"\",\"52\":\"\",\"\":0},\"plane0\":{\"0\":\"1\",\"1\":\"4\",\"2\":\"8\",\"3\":\"6\",\"4\":\"14\",\"5\":\"1\",\"6\":\"0\",\"7\":\"25\",\"40\":\"\",\"41\":\"\",\"42\":\"\",\"43\":\"\",\"44\":\"\",\"45\":\"\",\"46\":\"\",\"47\":\"\",\"48\":\"\",\"49\":\"\",\"50\":\"\",\"51\":\"\",\"52\":\"\",\"\":0},\"plane1\":{\"0\":\"2\",\"1\":\"5\",\"2\":\"9\",\"3\":\"7\",\"4\":\"0\",\"5\":\"2\",\"6\":\"0\",\"7\":\"0\",\"40\":\"\",\"41\":\"\",\"42\":\"\",\"43\":\"\",\"44\":\"\",\"45\":\"\",\"46\":\"\",\"47\":\"\",\"48\":\"\",\"49\":\"\",\"50\":\"\",\"51\":\"\",\"52\":\"\",\"\":0},\"plane2\":{\"0\":\"2\",\"1\":\"0\",\"2\":\"0\",\"3\":\"0\",\"4\":\"0\",\"5\":\"3\",\"6\":\"0\",\"7\":\"0\",\"40\":\"\",\"41\":\"\",\"42\":\"\",\"43\":\"\",\"44\":\"\",\"45\":\"\",\"46\":\"\",\"47\":\"\",\"48\":\"\",\"49\":\"\",\"50\":\"\",\"51\":\"\",\"52\":\"\",\"\":0},\"plane3\":{\"0\":\"0\",\"1\":\"0\",\"2\":\"0\",\"3\":\"0\",\"4\":\"0\",\"5\":\"0\",\"6\":\"0\",\"7\":\"0\",\"40\":\"\",\"41\":\"\",\"42\":\"\",\"43\":\"\",\"44\":\"\",\"45\":\"\",\"46\":\"\",\"47\":\"\",\"48\":\"\",\"49\":\"\",\"50\":\"\",\"51\":\"\",\"52\":\"\",\"\":0},\"skill\":{\"0\":\"1\",\"1\":\"0\",\"2\":\"0\",\"3\":\"0\",\"4\":\"0\",\"5\":\"0\",\"6\":\"0\",\"7\":\"0\",\"40\":\"\",\"41\":\"\",\"42\":\"\",\"43\":\"\",\"44\":\"\",\"45\":\"\",\"46\":\"\",\"47\":\"\",\"48\":\"\",\"49\":\"\",\"50\":\"\",\"51\":\"\",\"52\":\"\",\"\":0},\"equip0\":{\"0\":\"2\",\"1\":\"16\",\"2\":\"8\",\"3\":\"0\",\"4\":\"47\",\"5\":\"0\",\"6\":\"17\",\"7\":\"48\",\"40\":\"\",\"41\":\"\",\"42\":\"\",\"43\":\"\",\"44\":\"\",\"45\":\"\",\"46\":\"\",\"47\":\"\",\"48\":\"\",\"49\":\"\",\"50\":\"\",\"51\":\"\",\"52\":\"\",\"\":0},\"equip1\":{\"0\":\"30\",\"1\":\"23\",\"2\":\"7\",\"3\":\"0\",\"4\":\"0\",\"5\":\"0\",\"6\":\"0\",\"7\":\"0\",\"40\":\"\",\"41\":\"\",\"42\":\"\",\"43\":\"\",\"44\":\"\",\"45\":\"\",\"46\":\"\",\"47\":\"\",\"48\":\"\",\"49\":\"\",\"50\":\"\",\"51\":\"\",\"52\":\"\",\"\":0},\"equip2\":{\"0\":\"0\",\"1\":\"25\",\"2\":\"0\",\"3\":\"0\",\"4\":\"0\",\"5\":\"0\",\"6\":\"0\",\"7\":\"0\",\"40\":\"\",\"41\":\"\",\"42\":\"\",\"43\":\"\",\"44\":\"\",\"45\":\"\",\"46\":\"\",\"47\":\"\",\"48\":\"\",\"49\":\"\",\"50\":\"\",\"51\":\"\",\"52\":\"\",\"\":0},\"queue0\":{\"0\":\"1\",\"1\":\"1\",\"2\":\"1\",\"3\":\"1\",\"4\":\"1\",\"5\":\"1\",\"6\":\"1\",\"7\":\"1\",\"40\":\"\",\"41\":\"\",\"42\":\"\",\"43\":\"\",\"44\":\"\",\"45\":\"\",\"46\":\"\",\"47\":\"\",\"48\":\"\",\"49\":\"\",\"50\":\"\",\"51\":\"\",\"52\":\"\",\"\":0},\"queue1\":{\"0\":\"2\",\"1\":\"2\",\"2\":\"2\",\"3\":\"2\",\"4\":\"2\",\"5\":\"2\",\"6\":\"2\",\"7\":\"2\",\"40\":\"\",\"41\":\"\",\"42\":\"\",\"43\":\"\",\"44\":\"\",\"45\":\"\",\"46\":\"\",\"47\":\"\",\"48\":\"\",\"49\":\"\",\"50\":\"\",\"51\":\"\",\"52\":\"\",\"\":0},\"queue2\":{\"0\":\"3\",\"1\":\"3\",\"2\":\"3\",\"3\":\"3\",\"4\":\"3\",\"5\":\"3\",\"6\":\"3\",\"7\":\"3\",\"40\":\"\",\"41\":\"\",\"42\":\"\",\"43\":\"\",\"44\":\"\",\"45\":\"\",\"46\":\"\",\"47\":\"\",\"48\":\"\",\"49\":\"\",\"50\":\"\",\"51\":\"\",\"52\":\"\",\"\":0}},\"keys\":[\"name\",\"info\",\"condition\",\"hp\",\"lead\",\"spd\",\"dmg\",\"mov\",\"luc\",\"average\",\"plane0\",\"plane1\",\"plane2\",\"plane3\",\"skill\",\"equip0\",\"equip1\",\"equip2\",\"queue0\",\"queue1\",\"queue2\"],\"items\":[\"0\",\"1\",\"2\",\"3\",\"4\",\"5\",\"6\",\"7\",\"\",\"\",\"\",\"\",\"\",\"\",\"\",\"\",\"\",\"\",\"\",\"\",\"\",\"\",\"\",\"\",\"\",\"\",\"\",\"\",\"\",\"\",\"\",\"\",\"\",\"\",\"\",\"\",\"\",\"\",\"\",\"\",\"40\",\"41\",\"42\",\"43\",\"44\",\"45\",\"46\",\"47\",\"48\",\"49\",\"50\",\"51\",\"52\",\"\"]}","achievement":"{\"table\":{\"name\":{\"0\":\"开始的战役\",\"1\":\"时间穿梭\",\"2\":\"永不放弃\",\"3\":\"无尽轮回\",\"4\":\"探索者\",\"5\":\"专业冒险家\",\"6\":\"星球研究员\",\"7\":\"时间的循环点\",\"8\":\"打破的循环\",\"9\":\"莫比乌斯环\",\"10\":\"毁灭者I\",\"11\":\"毁灭者II\",\"12\":\"毁灭者III\",\"13\":\"毁灭者IV\",\"14\":\"毁灭者V\",\"15\":\"收藏新手\",\"16\":\"收藏高手\",\"17\":\"收藏专家\",\"18\":\"收藏大师\",\"19\":\"收藏之神\",\"20\":\"完美评价I\",\"21\":\"完美评价II\",\"22\":\"完美评价III\",\"23\":\"完美评价IV\",\"24\":\"不错评价I\",\"25\":\"不错评价II\",\"26\":\"不错评价III\",\"27\":\"不错评价IV\",\"28\":\"海盗I\",\"29\":\"海盗II\",\"30\":\"海盗III\",\"31\":\"海盗IV\",\"32\":\"能源开发I\",\"33\":\"能源开发II\",\"34\":\"能源开发III\",\"35\":\"能源开发IV\",\"36\":\"科技实验I\",\"37\":\"科技实验II\",\"38\":\"科技实验III\",\"39\":\"科技实验IV\",\"40\":\"装备收藏家I\",\"41\":\"装备收藏家II\",\"42\":\"装备收藏家III\",\"43\":\"装备收藏家IV\",\"44\":\"商人I\",\"45\":\"商人II\",\"46\":\"商人III\",\"47\":\"商人IV\",\"48\":\"第一个星系币\",\"49\":\"星系币II\",\"50\":\"星系币III\",\"51\":\"星系币IV\",\"52\":\"旅行家I\",\"53\":\"旅行家II\",\"54\":\"旅行家III\",\"55\":\"破壁者I\",\"56\":\"破壁者II\",\"57\":\"破壁者III\",\"58\":\"通关I\",\"59\":\"通关II\",\"60\":\"通关III\",\"61\":\"无尽挑战I\",\"62\":\"无尽挑战II\",\"63\":\"无尽挑战III\",\"\":0},\"info\":{\"0\":\"首次进入游戏获得\",\"1\":\"玩第3次游戏时获得\",\"2\":\"玩第10次游戏时获得\",\"3\":\"玩第100次游戏时获得\",\"4\":\"打通10个星球\",\"5\":\"打通50个星球\",\"6\":\"打通300个星球\",\"7\":\"首次通关游戏(简单模式)\",\"8\":\"首次通关游戏(困难模式)\",\"9\":\"首次通关游戏(地狱模式)\",\"10\":\"消灭敌人飞机50架\",\"11\":\"消灭敌人飞机100架\",\"12\":\"消灭敌人飞机1000架\",\"13\":\"消灭敌人飞机5000架\",\"14\":\"消灭敌人飞机10000架\",\"15\":\"图纸收集率超过15%\",\"16\":\"图纸收集率超过35%\",\"17\":\"图纸收集率超过65%\",\"18\":\"图纸收集率超过85%\",\"19\":\"图纸收集率达到100%\",\"20\":\"通关获得 S级以上 1次\",\"21\":\"通关获得 S级以上 3次\",\"22\":\"通关获得 S级以上 10次\",\"23\":\"通关获得 S级以上 30次\",\"24\":\"通关获得 A级以上 3次\",\"25\":\"通关获得 A级以上 15次\",\"26\":\"通关获得 A级以上 50次\",\"27\":\"通关获得 A级以上 100次\",\"28\":\"战斗累计收集10000G\",\"29\":\"战斗累计收集50000G\",\"30\":\"战斗累计收集150000G\",\"31\":\"战斗累计收集500000G\",\"32\":\"战斗累计收1000能源\",\"33\":\"战斗累计收5000能源\",\"34\":\"战斗累计收10000能源\",\"35\":\"战斗累计收50000能源\",\"36\":\"战斗累计使用技能10次\",\"37\":\"战斗累计使用技能100次\",\"38\":\"战斗累计使用技能500次\",\"39\":\"战斗累计使用技能1000次\",\"40\":\"战斗累计获得装备20次\",\"41\":\"战斗累计获得装备200次\",\"42\":\"战斗累计获得装备100次\",\"43\":\"战斗累计获得装备2000次\",\"44\":\"累计购买 10次\",\"45\":\"累计购买 200次\",\"46\":\"累计购买 1000次\",\"47\":\"累计购买 3000次\",\"48\":\"战斗累计获得 1 个星系币\",\"49\":\"战斗累计获得 9 个 星系币\",\"50\":\"战斗累计获得 99 个 星系币\",\"51\":\"战斗累计获得 999 个 星系币\",\"52\":\"旅行距离超过9999\",\"53\":\"旅行距离超过99999\",\"54\":\"旅行距离超过999999\",\"55\":\"通关最高得分10000\",\"56\":\"通关最高得分100000\",\"57\":\"通关最高得分900000\",\"58\":\"任意难度游戏通关次数5次\",\"59\":\"任意难度游戏通关次数25次\",\"60\":\"任意难度游戏通关次数100次\",\"61\":\"通关过最远关卡数 9关\",\"62\":\"通关过最远关卡数 19关\",\"63\":\"通关过最远关卡数 29关\",\"\":0},\"valueName\":{\"0\":\"game_count\",\"1\":\"game_count\",\"2\":\"game_count\",\"3\":\"game_count\",\"4\":\"planet_finish\",\"5\":\"planet_finish\",\"6\":\"planet_finish\",\"7\":\"game_mode_normal\",\"8\":\"game_mode_hard\",\"9\":\"game_mode_extra\",\"10\":\"enemy_kills\",\"11\":\"enemy_kills\",\"12\":\"enemy_kills\",\"13\":\"enemy_kills\",\"14\":\"enemy_kills\",\"15\":\"collect_per\",\"16\":\"collect_per\",\"17\":\"collect_per\",\"18\":\"collect_per\",\"19\":\"collect_per\",\"20\":\"rank_s\",\"21\":\"rank_s\",\"22\":\"rank_s\",\"23\":\"rank_s\",\"24\":\"rank_a\",\"25\":\"rank_a\",\"26\":\"rank_a\",\"27\":\"rank_a\",\"28\":\"collect_coin\",\"29\":\"collect_coin\",\"30\":\"collect_coin\",\"31\":\"collect_coin\",\"32\":\"collect_energy\",\"33\":\"collect_energy\",\"34\":\"collect_energy\",\"35\":\"collect_energy\",\"36\":\"use_skill_count\",\"37\":\"use_skill_count\",\"38\":\"use_skill_count\",\"39\":\"use_skill_count\",\"40\":\"get_equip_count\",\"41\":\"get_equip_count\",\"42\":\"get_equip_count\",\"43\":\"get_equip_count\",\"44\":\"buy_count\",\"45\":\"buy_count\",\"46\":\"buy_count\",\"47\":\"buy_count\",\"48\":\"collect_gem\",\"49\":\"collect_gem\",\"50\":\"collect_gem\",\"51\":\"collect_gem\",\"52\":\"travel_distance\",\"53\":\"travel_distance\",\"54\":\"travel_distance\",\"55\":\"high_score\",\"56\":\"high_score\",\"57\":\"high_score\",\"58\":\"game_clear\",\"59\":\"game_clear\",\"60\":\"game_clear\",\"61\":\"high_level\",\"62\":\"high_level\",\"63\":\"high_level\",\"\":0},\"target\":{\"0\":\"1\",\"1\":\"3\",\"2\":\"10\",\"3\":\"100\",\"4\":\"10\",\"5\":\"50\",\"6\":\"300\",\"7\":\"1\",\"8\":\"1\",\"9\":\"1\",\"10\":\"50\",\"11\":\"100\",\"12\":\"1000\",\"13\":\"5000\",\"14\":\"10000\",\"15\":\"15\",\"16\":\"35\",\"17\":\"65\",\"18\":\"85\",\"19\":\"100\",\"20\":\"1\",\"21\":\"3\",\"22\":\"10\",\"23\":\"30\",\"24\":\"3\",\"25\":\"15\",\"26\":\"50\",\"27\":\"100\",\"28\":\"10000\",\"29\":\"50000\",\"30\":\"150000\",\"31\":\"500000\",\"32\":\"1000\",\"33\":\"5000\",\"34\":\"10000\",\"35\":\"50000\",\"36\":\"10\",\"37\":\"100\",\"38\":\"500\",\"39\":\"1000\",\"40\":\"20\",\"41\":\"200\",\"42\":\"100\",\"43\":\"2000\",\"44\":\"10\",\"45\":\"200\",\"46\":\"1000\",\"47\":\"3000\",\"48\":\"1\",\"49\":\"9\",\"50\":\"99\",\"51\":\"999\",\"52\":\"9999\",\"53\":\"99999\",\"54\":\"999999\",\"55\":\"10000\",\"56\":\"100000\",\"57\":\"900000\",\"58\":\"5\",\"59\":\"25\",\"60\":\"100\",\"61\":\"9\",\"62\":\"19\",\"63\":\"29\",\"\":0},\"point\":{\"0\":\"1\",\"1\":\"2\",\"2\":\"5\",\"3\":\"10\",\"4\":\"1\",\"5\":\"3\",\"6\":\"5\",\"7\":\"10\",\"8\":\"20\",\"9\":\"50\",\"10\":\"1\",\"11\":\"2\",\"12\":\"5\",\"13\":\"10\",\"14\":\"25\",\"15\":\"3\",\"16\":\"15\",\"17\":\"30\",\"18\":\"50\",\"19\":\"88\",\"20\":\"6\",\"21\":\"20\",\"22\":\"50\",\"23\":\"80\",\"24\":\"3\",\"25\":\"10\",\"26\":\"25\",\"27\":\"50\",\"28\":\"2\",\"29\":\"12\",\"30\":\"30\",\"31\":\"50\",\"32\":\"2\",\"33\":\"12\",\"34\":\"30\",\"35\":\"50\",\"36\":\"2\",\"37\":\"10\",\"38\":\"20\",\"39\":\"45\",\"40\":\"3\",\"41\":\"15\",\"42\":\"45\",\"43\":\"60\",\"44\":\"2\",\"45\":\"14\",\"46\":\"30\",\"47\":\"60\",\"48\":\"3\",\"49\":\"10\",\"50\":\"50\",\"51\":\"90\",\"52\":\"2\",\"53\":\"8\",\"54\":\"16\",\"55\":\"4\",\"56\":\"8\",\"57\":\"20\",\"58\":\"5\",\"59\":\"15\",\"60\":\"50\",\"61\":\"4\",\"62\":\"10\",\"63\":\"50\",\"\":0},\"deployment\":{\"0\":\"*\",\"1\":\"*\",\"2\":\"*\",\"3\":\"*\",\"4\":\"*\",\"5\":\"*\",\"6\":\"*\",\"7\":\"*\",\"8\":\"*\",\"9\":\"*\",\"10\":\"*\",\"11\":\"*\",\"12\":\"*\",\"13\":\"*\",\"14\":\"*\",\"15\":\"*\",\"16\":\"*\",\"17\":\"*\",\"18\":\"*\",\"19\":\"*\",\"20\":\"*\",\"21\":\"*\",\"22\":\"*\",\"23\":\"*\",\"24\":\"*\",\"25\":\"*\",\"26\":\"*\",\"27\":\"*\",\"28\":\"*\",\"29\":\"*\",\"30\":\"*\",\"31\":\"*\",\"32\":\"*\",\"33\":\"*\",\"34\":\"*\",\"35\":\"*\",\"36\":\"*\",\"37\":\"*\",\"38\":\"*\",\"39\":\"*\",\"40\":\"*\",\"41\":\"*\",\"42\":\"*\",\"43\":\"*\",\"44\":\"*\",\"45\":\"*\",\"46\":\"*\",\"47\":\"*\",\"48\":\"*\",\"49\":\"*\",\"50\":\"*\",\"51\":\"*\",\"52\":\"*\",\"53\":\"*\",\"54\":\"*\",\"55\":\"*\",\"56\":\"*\",\"57\":\"*\",\"58\":\"*\",\"59\":\"*\",\"60\":\"*\",\"61\":\"*\",\"62\":\"*\",\"63\":\"*\",\"\":0},\"tag\":{\"0\":\"游戏局数\",\"1\":\"游戏局数\",\"2\":\"游戏局数\",\"3\":\"游戏局数\",\"4\":\"抵达星球\",\"5\":\"抵达星球\",\"6\":\"抵达星球\",\"7\":\"简单通关\",\"8\":\"普通通关\",\"9\":\"困难通关\",\"10\":\"消灭敌机\",\"11\":\"消灭敌机\",\"12\":\"消灭敌机\",\"13\":\"消灭敌机\",\"14\":\"消灭敌机\",\"15\":\"图纸收集率\",\"16\":\"图纸收集率\",\"17\":\"图纸收集率\",\"18\":\"图纸收集率\",\"19\":\"图纸收集率\",\"20\":\"S评价\",\"21\":\"S评价\",\"22\":\"S评价\",\"23\":\"S评价\",\"24\":\"A评价\",\"25\":\"A评价\",\"26\":\"A评价\",\"27\":\"A评价\",\"28\":\"收集金币\",\"29\":\"收集金币\",\"30\":\"收集金币\",\"31\":\"收集金币\",\"32\":\"收集能量\",\"33\":\"收集能量\",\"34\":\"收集能量\",\"35\":\"收集能量\",\"36\":\"使用技能\",\"37\":\"使用技能\",\"38\":\"使用技能\",\"39\":\"使用技能\",\"40\":\"获得装备\",\"41\":\"获得装备\",\"42\":\"获得装备\",\"43\":\"获得装备\",\"44\":\"购买商品\",\"45\":\"购买商品\",\"46\":\"购买商品\",\"47\":\"购买商品\",\"48\":\"收集星系币\",\"49\":\"收集星系币\",\"50\":\"收集星系币\",\"51\":\"收集星系币\",\"52\":\"航行距离\",\"53\":\"航行距离\",\"54\":\"航行距离\",\"55\":\"最高得分\",\"56\":\"最高得分\",\"57\":\"最高得分\",\"58\":\"完美通关\",\"59\":\"完美通关\",\"60\":\"完美通关\",\"61\":\"最高层数\",\"62\":\"最高层数\",\"63\":\"最高层数\",\"\":0}},\"keys\":[\"name\",\"info\",\"valueName\",\"target\",\"point\",\"deployment\",\"tag\"],\"items\":[\"0\",\"1\",\"2\",\"3\",\"4\",\"5\",\"6\",\"7\",\"8\",\"9\",\"10\",\"11\",\"12\",\"13\",\"14\",\"15\",\"16\",\"17\",\"18\",\"19\",\"20\",\"21\",\"22\",\"23\",\"24\",\"25\",\"26\",\"27\",\"28\",\"29\",\"30\",\"31\",\"32\",\"33\",\"34\",\"35\",\"36\",\"37\",\"38\",\"39\",\"40\",\"41\",\"42\",\"43\",\"44\",\"45\",\"46\",\"47\",\"48\",\"49\",\"50\",\"51\",\"52\",\"53\",\"54\",\"55\",\"56\",\"57\",\"58\",\"59\",\"60\",\"61\",\"62\",\"63\",\"\"]}","buff":"{\"table\":{\"value\":{\"【玩家属性】\":\"\",\"add_hp\":\"0\",\"add_lead\":\"0\",\"add_spd\":\"0\",\"add_dmg\":\"0\",\"add_mov\":\"0\",\"add_luc\":\"0\",\"【玩家附加属性】\":\"\",\"lucky_shoot_rate\":\"0\",\"lucky_shoot_dmg\":\"50\",\"line_shoot_random\":\"0\",\"scope_shoot_add\":\"0\",\"【敌人属性】\":\"\",\"enemy_hp\":\"0\",\"enemy_lead\":\"0\",\"enemy_spd\":\"0\",\"enemy_dmg\":\"0\",\"enemy_mov\":\"0\",\"enemy_size\":\"-90\",\"boss_hp_decrease\":\"0\",\"create_elite_double\":\"0\",\"create_more_enemy\":\"0\",\"enemy_bullet_size\":\"0\",\"【额外属性】\":\"\",\"ext_get_gold\":\"0\",\"ext_get_energy\":\"0\",\"ext_get_heal\":\"0\",\"hp_drop_rate\":\"10\",\"energy_drop_rate\":\"10\",\"item_drop_rate\":\"20\",\"gem_drop_rate\":\"5\",\"gold_drop_rate\":\"10\",\"shake_time_down\":\"0\",\"【地图属性】\":\"\",\"[创建]\":\"\",\"map_event_rate\":\"5\",\"map_shop_rate\":\"5\",\"map_energy_rate\":\"5\",\"map_gold_rate\":\"3\",\"planet_danger_increase\":\"0\",\"planet_cost\":\"10\",\"[事件]\":\"\",\"event_off_max\":\"20\",\"[商店]\":\"\",\"shop_off_rate\":\"5\",\"shop_off_max\":\"20\",\"【Systtem 系统规则buff】\":\"\",\"item_delete_lock\":\"0\",\"queue_break\":\"0\",\"myplane_recycle\":\"0\",\"game_speed\":\"0\",\"travel_distance_double\":\"0\",\"gui_damage_show\":\"0\",\"gui_hpbar_show\":\"0\",\"gui_danger_check\":\"0\",\"gui_plane_info\":\"0\",\"【特殊能力】\":\"\",\"danger_trigger\":\"0\",\"auto_heal\":\"0\",\"all_one_kill\":\"0\",\"death_skill_use\":\"0\",\"break_danger_switch\":\"0\"},\"max\":{\"【玩家属性】\":\"\",\"add_hp\":\"999\",\"add_lead\":\"999\",\"add_spd\":\"999\",\"add_dmg\":\"999\",\"add_mov\":\"999\",\"add_luc\":\"999\",\"【玩家附加属性】\":\"\",\"lucky_shoot_rate\":\"100\",\"lucky_shoot_dmg\":\"500\",\"line_shoot_random\":\"45\",\"scope_shoot_add\":\"3\",\"【敌人属性】\":\"\",\"enemy_hp\":\"999\",\"enemy_lead\":\"999\",\"enemy_spd\":\"999\",\"enemy_dmg\":\"999\",\"enemy_mov\":\"999\",\"enemy_size\":\"100\",\"boss_hp_decrease\":\"50\",\"create_elite_double\":\"1\",\"create_more_enemy\":\"10\",\"enemy_bullet_size\":\"100\",\"【额外属性】\":\"\",\"ext_get_gold\":\"5\",\"ext_get_energy\":\"5\",\"ext_get_heal\":\"10\",\"hp_drop_rate\":\"100\",\"energy_drop_rate\":\"100\",\"item_drop_rate\":\"100\",\"gem_drop_rate\":\"100\",\"gold_drop_rate\":\"100\",\"shake_time_down\":\"100\",\"【地图属性】\":\"\",\"[创建]\":\"\",\"map_event_rate\":\"100\",\"map_shop_rate\":\"100\",\"map_energy_rate\":\"100\",\"map_gold_rate\":\"100\",\"planet_danger_increase\":\"100\",\"planet_cost\":\"100\",\"[事件]\":\"\",\"event_off_max\":\"99\",\"[商店]\":\"\",\"shop_off_rate\":\"50\",\"shop_off_max\":\"99\",\"【Systtem 系统规则buff】\":\"\",\"item_delete_lock\":\"1\",\"queue_break\":\"1\",\"myplane_recycle\":\"1\",\"game_speed\":\"200\",\"travel_distance_double\":\"1\",\"gui_damage_show\":\"1\",\"gui_hpbar_show\":\"1\",\"gui_danger_check\":\"1\",\"gui_plane_info\":\"1\",\"【特殊能力】\":\"\",\"danger_trigger\":\"1\",\"auto_heal\":\"1\",\"all_one_kill\":\"1\",\"death_skill_use\":\"99\",\"break_danger_switch\":\"60\"},\"info\":{\"【玩家属性】\":\"\",\"add_hp\":\"额外生命属性(%)\",\"add_lead\":\"额外领导属性(%)\",\"add_spd\":\"额外射速属性(%)\",\"add_dmg\":\"额外伤害属性(%)\",\"add_mov\":\"额外移速属性(%)\",\"add_luc\":\"额外幸运属性(%)\",\"【玩家附加属性】\":\"\",\"lucky_shoot_rate\":\"幸运一射几率(%)\",\"lucky_shoot_dmg\":\"幸运一射伤害追加值(%)\",\"line_shoot_random\":\"射击不稳定性(%)\",\"scope_shoot_add\":\"散弹数量追加\",\"【敌人属性】\":\"\",\"enemy_hp\":\"(敌人)额外生命属性(%)\",\"enemy_lead\":\"(敌人)额外领导属性(%)\",\"enemy_spd\":\"(敌人)额外射速属性(%)\",\"enemy_dmg\":\"(敌人)额外伤害属性(%)\",\"enemy_mov\":\"(敌人)额外移速属性(%)\",\"enemy_size\":\"(敌人)的体积缩放(%)\",\"boss_hp_decrease\":\"(BOSS)的初始HP削弱\",\"create_elite_double\":\"双生精英敌人\",\"create_more_enemy\":\"更多敌人追加\",\"enemy_bullet_size\":\"敌人子弹的尺寸增加比(%)\",\"【额外属性】\":\"\",\"ext_get_gold\":\"额外获得金币数(X)\",\"ext_get_energy\":\"额外获得能量数(X)\",\"ext_get_heal\":\"额外恢复率(%)\",\"hp_drop_rate\":\"恢复道具掉落概率(%)\",\"energy_drop_rate\":\"能量掉落概率(%)\",\"item_drop_rate\":\"其他道具掉落概率(%)\",\"gem_drop_rate\":\"额外 星系币 掉落率(%)\",\"gold_drop_rate\":\"金钱掉落概率(%)\",\"shake_time_down\":\"缩短硬直时间(%)\",\"【地图属性】\":\"\",\"[创建]\":\"\",\"map_event_rate\":\"地图出现事件的概率(%)\",\"map_shop_rate\":\"地图出现商店的概率(%)\",\"map_energy_rate\":\"地图出现能量矿的概率(%)\",\"map_gold_rate\":\"地图出现金矿的概率(%)\",\"planet_danger_increase\":\"基础危险值上升率(%)\",\"planet_cost\":\"星球能量消耗基础值\",\"[事件]\":\"\",\"event_off_max\":\"交易事件默认折扣力度(-%)\",\"[商店]\":\"\",\"shop_off_rate\":\"商店折扣出现概率(%)\",\"shop_off_max\":\"商店折扣最大值(%)\",\"【Systtem 系统规则buff】\":\"独立buff属于特殊buff\",\"item_delete_lock\":\"道具删除锁定\",\"queue_break\":\"队列随机切换移动\",\"myplane_recycle\":\"我的飞机回收\",\"game_speed\":\"敌人行动速度\",\"travel_distance_double\":\"旅行距离双倍\",\"gui_damage_show\":\"显示全场子弹造成的伤害值\",\"gui_hpbar_show\":\"显示敌人的血条\",\"gui_danger_check\":\"危险检测器\",\"gui_plane_info\":\"详细信息\",\"【特殊能力】\":\"\",\"danger_trigger\":\"危险扳机\",\"auto_heal\":\"自动修复\",\"all_one_kill\":\"全部归1\",\"death_skill_use\":\"(值为 技能ID值)\",\"break_danger_switch\":\"推迟时间\"},\"introduce\":{\"【玩家属性】\":\"\",\"add_hp\":\"新创建飞船可以增加生命\",\"add_lead\":\"增加飞船的持有数\",\"add_spd\":\"增加射速\",\"add_dmg\":\"增加额外伤害值\",\"add_mov\":\"增加额外移动速度\",\"add_luc\":\"增加额外幸运值(幸运值会影响大部分概率事件)\",\"【玩家附加属性】\":\"\",\"lucky_shoot_rate\":\"隐藏属性，发动幸运射击，子弹威力会大幅提升\",\"lucky_shoot_dmg\":\"幸运一击的最大伤害加成值\",\"line_shoot_random\":\"对直线射击的弹幕 由直线变得不稳定(散射)\",\"scope_shoot_add\":\"增加散射子弹的 子弹数量??\",\"【敌人属性】\":\"\",\"enemy_hp\":\"(敌人)新创建飞船可以增加生命\",\"enemy_lead\":\"(敌人)增加飞船的持有数(10点为1个)\",\"enemy_spd\":\"(敌人)增加射速\",\"enemy_dmg\":\"(敌人)增加额外伤害值\",\"enemy_mov\":\"(敌人)增加额外移动速度\",\"enemy_size\":\"(敌人)体积发生变化\",\"boss_hp_decrease\":\"(BOSS)初始HP削弱\",\"create_elite_double\":\"精英敌人出现时，会出现两架\",\"create_more_enemy\":\"会出现更多敌人\",\"enemy_bullet_size\":\"可以正或者负数\",\"【额外属性】\":\"\",\"ext_get_gold\":\"获得金币时 奖励的数量，只对敌人掉落金币加成\",\"ext_get_energy\":\"获得能量时 奖励的数量,只对敌人掉落能量加成\",\"ext_get_heal\":\"获得恢复道具时候，效果增加50%\",\"hp_drop_rate\":\"敌人掉落恢复品的概率\",\"energy_drop_rate\":\"敌人掉落能量石的概率\",\"item_drop_rate\":\"敌人掉落道具的概率\",\"gem_drop_rate\":\"获得额外星系币的概率，一般+1\",\"gold_drop_rate\":\"获得金钱的概率, \",\"shake_time_down\":\"被子弹击中后飞机失控时间降低\",\"【地图属性】\":\"\",\"[创建]\":\"\",\"map_event_rate\":\"地图出现事件的概率\",\"map_shop_rate\":\"地图出现商店的概率\",\"map_energy_rate\":\"地图出现能量矿概率\",\"map_gold_rate\":\"地图出现金矿概率\",\"planet_danger_increase\":\"增加基础星球的危险值\",\"planet_cost\":\"10* 通过的Level* danger = 最终星球需要花费的能量\",\"[事件]\":\"\",\"event_off_max\":\"影响事件的最低消费值\",\"[商店]\":\"\",\"shop_off_rate\":\"影响折扣出现的概率\",\"shop_off_max\":\"影响出现的最大折扣值\",\"【Systtem 系统规则buff】\":\"每项都只会影响局部的系统功能\",\"item_delete_lock\":\"无法删除已经装备上的 任何一个道具\",\"queue_break\":\"玩家被干扰,不再按指令，而是进行随机化的队列切换\",\"myplane_recycle\":\"飞机被破坏时候，会根据价值产生一些金币(回收用)\",\"game_speed\":\"整体的速度发生改变(注意只会改变敌人移动速度,BOSS无效)\",\"travel_distance_double\":\"旅行距离双倍,缩短一半旅行的时间\",\"gui_damage_show\":\"GUI能力,显示子弹伤害值\",\"gui_hpbar_show\":\"GUI能力,显示敌人的血条\",\"gui_danger_check\":\"GUI能力，危险的攻击前会有提示\",\"gui_plane_info\":\"屏幕中显示所有飞机的综合能力\",\"【特殊能力】\":\"\",\"danger_trigger\":\"体力比率低于25%，飞机攻击力提高2倍\",\"auto_heal\":\"体力低于50% 时候 会缓慢的恢复一些体力\",\"all_one_kill\":\"玩家和敌人都会被一击必杀,但对BOSS只是增强伤害\",\"death_skill_use\":\"玩家如果飞机被销毁 会发动一个ID 的死亡技能\",\"break_danger_switch\":\"推迟机关陷阱的出现时间\"},\"deployment\":{\"【玩家属性】\":\"已配置?\",\"add_hp\":\"*\",\"add_lead\":\"*\",\"add_spd\":\"*\",\"add_dmg\":\"*\",\"add_mov\":\"*\",\"add_luc\":\"*\",\"【玩家附加属性】\":\"\",\"lucky_shoot_rate\":\"\",\"lucky_shoot_dmg\":\"\",\"line_shoot_random\":\"*\",\"scope_shoot_add\":\"*\",\"【敌人属性】\":\"\",\"enemy_hp\":\"*\",\"enemy_lead\":\"*\",\"enemy_spd\":\"*\",\"enemy_dmg\":\"*\",\"enemy_mov\":\"*\",\"enemy_size\":\"*\",\"boss_hp_decrease\":\"*\",\"create_elite_double\":\"*\",\"create_more_enemy\":\"\",\"enemy_bullet_size\":\"*\",\"【额外属性】\":\"\",\"ext_get_gold\":\"*\",\"ext_get_energy\":\"*\",\"ext_get_heal\":\"*\",\"hp_drop_rate\":\"*\",\"energy_drop_rate\":\"*\",\"item_drop_rate\":\"*\",\"gem_drop_rate\":\"*\",\"gold_drop_rate\":\"*\",\"shake_time_down\":\"*\",\"【地图属性】\":\"\",\"[创建]\":\"\",\"map_event_rate\":\"*\",\"map_shop_rate\":\"*\",\"map_energy_rate\":\"*\",\"map_gold_rate\":\"*\",\"planet_danger_increase\":\"*\",\"planet_cost\":\"*\",\"[事件]\":\"\",\"event_off_max\":\"*\",\"[商店]\":\"\",\"shop_off_rate\":\"*\",\"shop_off_max\":\"*\",\"【Systtem 系统规则buff】\":\"\",\"item_delete_lock\":\"*\",\"queue_break\":\"*\",\"myplane_recycle\":\"*\",\"game_speed\":\"*\",\"travel_distance_double\":\"*\",\"gui_damage_show\":\"*\",\"gui_hpbar_show\":\"*\",\"gui_danger_check\":\"\",\"gui_plane_info\":\"*\",\"【特殊能力】\":\"\",\"danger_trigger\":\"*\",\"auto_heal\":\"*\",\"all_one_kill\":\"*\",\"death_skill_use\":\"*\",\"break_danger_switch\":\"*\"}},\"keys\":[\"value\",\"max\",\"info\",\"introduce\",\"deployment\"],\"items\":[\"【玩家属性】\",\"add_hp\",\"add_lead\",\"add_spd\",\"add_dmg\",\"add_mov\",\"add_luc\",\"【玩家附加属性】\",\"lucky_shoot_rate\",\"lucky_shoot_dmg\",\"line_shoot_random\",\"scope_shoot_add\",\"\",\"【敌人属性】\",\"enemy_hp\",\"enemy_lead\",\"enemy_spd\",\"enemy_dmg\",\"enemy_mov\",\"enemy_size\",\"boss_hp_decrease\",\"create_elite_double\",\"create_more_enemy\",\"enemy_bullet_size\",\"\",\"【额外属性】\",\"ext_get_gold\",\"ext_get_energy\",\"ext_get_heal\",\"hp_drop_rate\",\"energy_drop_rate\",\"item_drop_rate\",\"gem_drop_rate\",\"gold_drop_rate\",\"shake_time_down\",\"\",\"【地图属性】\",\"[创建]\",\"map_event_rate\",\"map_shop_rate\",\"map_energy_rate\",\"map_gold_rate\",\"\",\"planet_danger_increase\",\"planet_cost\",\"\",\"[事件]\",\"event_off_max\",\"\",\"[商店]\",\"shop_off_rate\",\"shop_off_max\",\"\",\"\",\"\",\"【Systtem 系统规则buff】\",\"item_delete_lock\",\"queue_break\",\"myplane_recycle\",\"game_speed\",\"travel_distance_double\",\"\",\"gui_damage_show\",\"gui_hpbar_show\",\"gui_danger_check\",\"gui_plane_info\",\"\",\"【特殊能力】\",\"danger_trigger\",\"auto_heal\",\"all_one_kill\",\"death_skill_use\",\"break_danger_switch\",\"\"]}","planet":"{\"table\":{\"name\":{\"0\":\"未知星系\",\"1\":\"4399格林星\",\"2\":\"4399深蓝星\",\"3\":\"4399恶梦星\",\"4\":\"4399奥博斯特\",\"5\":\"4399赤红星\",\"6\":\"4399环海星\",\"7\":\"4399炼狱星\",\"8\":\"4399霜冻星\",\"9\":\"4399终焉之星\",\"10\":\"??之星\",\"ex1\":\"机械危机\",\"ex2\":\"最终毁灭\",\"\":0},\"info\":{\"0\":\"未知的星系\",\"1\":\"平和的星系，威胁不大\",\"2\":\"深蓝色的星球\",\"3\":\"恶梦笼罩的星球\",\"4\":\"特别发现的星球\",\"5\":\"赤红色的星球\",\"6\":\"海洋覆盖的星系\",\"7\":\"地狱的星球\",\"8\":\"霜冻的星球\",\"9\":\"最终的星球\",\"10\":\"未知的星球\",\"ex1\":\"BOSS星球\",\"ex2\":\"隐藏BOSS星球\",\"\":0},\"danger\":{\"0\":\"0\",\"1\":\"0.2\",\"2\":\"0.7\",\"3\":\"1.1\",\"4\":\"1.8\",\"5\":\"2.2\",\"6\":\"2.4\",\"7\":\"2.6\",\"8\":\"3.1\",\"9\":\"4.2\",\"10\":\"4.8\",\"ex1\":\"5.1\",\"ex2\":\"5.1\",\"\":0},\"rateValue\":{\"0\":\"0\",\"1\":\"30\",\"2\":\"30\",\"3\":\"20\",\"4\":\"5\",\"5\":\"20\",\"6\":\"20\",\"7\":\"15\",\"8\":\"20\",\"9\":\"20\",\"10\":\"10\",\"ex1\":\"5\",\"ex2\":\"5\",\"\":0},\"level\":{\"0\":\"1\",\"1\":\"1\",\"2\":\"1\",\"3\":\"2\",\"4\":\"2\",\"5\":\"3\",\"6\":\"4\",\"7\":\"5\",\"8\":\"6\",\"9\":\"7\",\"10\":\"8\",\"ex1\":\"-1\",\"ex2\":\"-2\",\"\":0},\"switchList\":{\"0\":\"未启用\",\"1\":\"未启用\",\"2\":\"未启用\",\"3\":\"未启用\",\"4\":\"未启用\",\"5\":\"未启用\",\"6\":\"未启用\",\"7\":\"未启用\",\"8\":\"未启用\",\"9\":\"未启用\",\"10\":\"未启用\",\"ex1\":\"未启用\",\"ex2\":\"未启用\",\"\":0},\"eliteList\":{\"0\":\"0\",\"1\":\"19|19\",\"2\":\"20|20\",\"3\":\"19|20|21\",\"4\":\"20|21|22\",\"5\":\"21|21|22\",\"6\":\"20|20|23\",\"7\":\"20|24|24\",\"8\":\"24|25|25\",\"9\":\"23|24|24\",\"10\":\"23|24|25\",\"ex1\":\"19|20|21|22|23|24|25\",\"ex2\":\"19|20|21|22|23|24|26\",\"\":0},\"boss\":{\"0\":\"-1\",\"1\":\"1\",\"2\":\"2\",\"3\":\"3\",\"4\":\"4\",\"5\":\"5\",\"6\":\"6\",\"7\":\"7\",\"8\":\"8\",\"9\":\"9\",\"10\":\"10\",\"ex1\":\"11\",\"ex2\":\"12\",\"\":0},\"\":{\"0\":\"\",\"1\":\"\",\"2\":\"\",\"3\":\"\",\"4\":\"\",\"5\":\"\",\"6\":\"\",\"7\":\"\",\"8\":\"\",\"9\":\"\",\"10\":\"\",\"ex1\":\"\",\"ex2\":\"\",\"\":0}},\"keys\":[\"name\",\"info\",\"danger\",\"rateValue\",\"level\",\"switchList\",\"eliteList\",\"boss\",\"\"],\"items\":[\"0\",\"1\",\"2\",\"3\",\"4\",\"5\",\"6\",\"7\",\"8\",\"9\",\"10\",\"ex1\",\"ex2\",\"\"]}","boss":"{\"table\":{\"name\":{\"0\":\"堡垒装甲·赛拉图\",\"1\":\"恶梦侵蚀·达尔科\",\"2\":\"紫色蝙蝠·巴尔特\",\"3\":\"变异甲虫·哈里斯\",\"4\":\"魔爪·灵子号\",\"5\":\"审判天使\",\"6\":\"污染腐蚀者\",\"7\":\"蓝色动力装甲\",\"8\":\"红色动力装甲\",\"9\":\"突袭黄蜂号\",\"10\":\"哈雷姆钢号\",\"\":0},\"title\":{\"0\":\"装甲\",\"1\":\"恶梦\",\"2\":\"蝙蝠\",\"3\":\"甲虫\",\"4\":\"魔爪射线\",\"5\":\"天使特性\",\"6\":\"腐蚀特性\",\"7\":\"火力全开\",\"8\":\"装甲强化\",\"9\":\"黄蜂搭载\",\"10\":\"最终兵器\",\"\":0},\"info\":{\"0\":\"初级装甲\\\\巡逻用飞船\\\\配备武器少\\\\但是防御性能不错\",\"1\":\"搭配高速射击武器\\\\让人难以应对。\",\"2\":\"搭载蝙蝠引擎\\\\强劲动力\\\\威力增幅\",\"3\":\"模仿变异昆虫制作的生化飞船\\\\非常危险。\",\"4\":\"搭载四个伸出的爪子会发生威力极强的激光。\",\"5\":\"白色涂装的飞船\\\\搭载人类未曾了解的科技\",\"6\":\"污染腐蚀之地的飞船\\\\机械受到侵蚀\\\\但是却能正常行驶\",\"7\":\"星系联盟生产的防卫装甲\\\\十分敏捷的动力装甲\",\"8\":\"星系联盟生产的防卫装甲\\\\装载大量武器的动力装甲\",\"9\":\"危险的黄色涂装机体\\\\会召唤黄蜂攻击\",\"10\":\"植入gate 跃迁引擎的最终兵器，拥有极强的破坏力\",\"\":0},\"skinAni\":{\"0\":\"boss0\",\"1\":\"boss1\",\"2\":\"boss2\",\"3\":\"boss3\",\"4\":\"boss4\",\"5\":\"boss5\",\"6\":\"boss6\",\"7\":\"boss7\",\"8\":\"boss8\",\"9\":\"boss9\",\"10\":\"boss10\",\"\":0},\"hp\":{\"0\":\"150\",\"1\":\"120\",\"2\":\"160\",\"3\":\"240\",\"4\":\"140\",\"5\":\"120\",\"6\":\"160\",\"7\":\"180\",\"8\":\"180\",\"9\":\"180\",\"10\":\"180\",\"\":0},\"atk\":{\"0\":\"50\",\"1\":\"60\",\"2\":\"70\",\"3\":\"80\",\"4\":\"90\",\"5\":\"100\",\"6\":\"100\",\"7\":\"80\",\"8\":\"95\",\"9\":\"140\",\"10\":\"140\",\"\":0},\"moveSpeed\":{\"0\":\"20\",\"1\":\"20\",\"2\":\"50\",\"3\":\"10\",\"4\":\"10\",\"5\":\"50\",\"6\":\"50\",\"7\":\"20\",\"8\":\"20\",\"9\":\"100\",\"10\":\"100\",\"\":0},\"shootSpeed\":{\"0\":\"20\",\"1\":\"20\",\"2\":\"10\",\"3\":\"5\",\"4\":\"10\",\"5\":\"10\",\"6\":\"10\",\"7\":\"10\",\"8\":\"10\",\"9\":\"20\",\"10\":\"20\",\"\":0},\"danger\":{\"0\":\"2\",\"1\":\"2\",\"2\":\"2.5\",\"3\":\"3\",\"4\":\"4\",\"5\":\"4.2\",\"6\":\"4.6\",\"7\":\"4.8\",\"8\":\"5\",\"9\":\"6\",\"10\":\"7.8\",\"\":0},\"gunList\":{\"0\":\"main|gun|gun|rnd|rnd|laser|laser\",\"1\":\"main|gun|gun|gun|gun|laser\",\"2\":\"main|laser|laser|circle|circle\",\"3\":\"main|gun|eye|eye\",\"4\":\"main|hand|hand|hand|hand|head\",\"5\":\"main|gun|gun|head\",\"6\":\"main|gun|hand|hand\",\"7\":\"main|gun|gun|triple|triple|mini|mini|mini|mini|head\",\"8\":\"main|head|gun|gun|circle|circle|circle|circle\",\"9\":\"main|gun|gun|gun|gun|circle|circle|circle|circle|laser|laser\",\"10\":\"main|point|point|gun|gun|head\",\"\":0},\"mode1\":{\"0\":\"line/0.4/0.9|rnd/0.2/0.5\",\"1\":\"line/0.2/0.5|laser/4/0.5\",\"2\":\"fan/0.4/0.5|wave/1/0.5\",\"3\":\"rnd/0.1/0.5|spread/0.5/0.2\",\"4\":\"rnd/1/0.5|line/1/0.2\",\"5\":\"rnd/0.4/0.5|line/0.5/0.8\",\"6\":\"spread/2/0.5|line/0.3/0.9\",\"7\":\"triple/0.5/0.5|mini/0.3/0.6\",\"8\":\"rnd/0.3/0.5|wave/0.6/0.3|rocket/0.6/0.5\",\"9\":\"line/0.6/0.8|rnd/0.6/0.3|bee/1/0.1\",\"10\":\"line/0.3/0.8|rnd/1/0.4\",\"\":0},\"mode2\":{\"0\":\"circle/0.15/0.7|rnd/0.2/0.5\",\"1\":\"rnd/0.2/0.5|laser/3/0.5\",\"2\":\"spread/0.2/0.8|laser/3/0.5|wave/0.5/0.5\",\"3\":\"rnd/0.1/0.5|spread/0.2/0.2|laser/3/0.8\",\"4\":\"rnd/0.5/0.5|line/0.5/0.2|laser/5/0.5\",\"5\":\"rnd/0.3/0.6|line/0.4/0.8|sht/3/0.5\",\"6\":\"blade/1/0.5|line/0.2/0.8|spread/1/0.7\",\"7\":\"line/0.4/0.8|triple/0.4/0.8|wave/1/0.6\",\"8\":\"rnd/0.2/0.7|fan/1/0.4|rocket/0.5/0.5\",\"9\":\"line/0.3/0.7|rocket/0.6/0.5|laser/4/0.5|bee/1/0.2\",\"10\":\"line/0.2/0.8|rnd/1/0.5|bom/1/0.2\",\"\":0},\"mode3\":{\"0\":\"circle/0.25/0.5|laser/2/0.5|rnd/0.2/0.5\",\"1\":\"line/0.2/0.5|rnd/0.2/0.5|laser/2/0.5\",\"2\":\"spread/0.2/0.5|fan/0.3/0.5|laser/2/0.5\",\"3\":\"rnd/0.1/0.5|spread/0.4/0.2|laser/1/0.5\",\"4\":\"rnd/0.5/0.9|line/0.4/0.3|laser/3/0.5\",\"5\":\"rnd/0.2/0.8|line/0.3/0.8|sht/2/0.5\",\"6\":\"blade/0.5/0.5|line/0.1/0.8|spread/0.5/0.5\",\"7\":\"triple/0.2/0.9|wave/0.8/0.8|mini/1/0.5\",\"8\":\"rnd/0.1/0.8|fan/0.7/0.5|rocket/0.3/0.5\",\"9\":\"line/0.1/0.7|rocket/0.6/0.5|laser/1/0.5|bee/1/0.3\",\"10\":\"line/0.2/0.5|rnd/1/0.3|bom/1/0.3\",\"\":0}},\"keys\":[\"name\",\"title\",\"info\",\"skinAni\",\"hp\",\"atk\",\"moveSpeed\",\"shootSpeed\",\"danger\",\"gunList\",\"mode1\",\"mode2\",\"mode3\"],\"items\":[\"0\",\"1\",\"2\",\"3\",\"4\",\"5\",\"6\",\"7\",\"8\",\"9\",\"10\",\"\"]}","story":"{\"table\":{\"name\":{\"note_0_E_A\":\"漫游日记1-A\",\"note_0_E_B\":\"漫游日记1-B\",\"note_0_E_C\":\"漫游日记1-C\",\"note_1_E_A\":\"海盗笔记1-A\",\"note_1_E_B\":\"海盗笔记1-B\",\"note_1_E_C\":\"海盗笔记1-C\",\"note_2_E_A\":\"星盟资料1-A\",\"note_2_E_B\":\"星盟资料1-B\",\"note_2_E_C\":\"星盟资料1-C\",\"note_3_E_A\":\"残缺资料1-A\",\"note_3_E_B\":\"残缺资料1-B\",\"note_3_E_C\":\"残缺资料1-C\",\"note_4_E_A\":\"芯片1-A\",\"note_4_E_B\":\"芯片1-B\",\"note_4_E_C\":\"芯片1-C\",\"note_5_E_A\":\"神秘笔记1-A\",\"note_5_E_B\":\"神秘笔记1-B\",\"note_5_E_C\":\"神秘笔记1-C\",\"note_6_E_A\":\"最终笔记1-A\",\"note_6_E_B\":\"最终笔记1-B\",\"note_6_E_C\":\"最终笔记1-C\",\"note_7_E_A\":\"领主报告1-A\",\"note_7_E_B\":\"领主报告1-B\",\"note_7_E_C\":\"领主报告1-C\",\"note_0_N_A\":\"漫游日记2-A\",\"note_0_N_B\":\"漫游日记2-B\",\"note_0_N_C\":\"漫游日记2-C\",\"note_1_N_A\":\"海盗笔记2-A\",\"note_1_N_B\":\"海盗笔记2-B\",\"note_1_N_C\":\"海盗笔记2-C\",\"note_2_N_A\":\"星盟资料2-A\",\"note_2_N_B\":\"星盟资料2-B\",\"note_2_N_C\":\"星盟资料2-C\",\"note_3_N_A\":\"残缺资料2-A\",\"note_3_N_B\":\"残缺资料2-B\",\"note_3_N_C\":\"残缺资料2-C\",\"note_4_N_A\":\"芯片2-A\",\"note_4_N_B\":\"芯片2-B\",\"note_4_N_C\":\"芯片2-C\",\"note_5_N_A\":\"神秘笔记2-A\",\"note_5_N_B\":\"神秘笔记2-B\",\"note_5_N_C\":\"神秘笔记2-C\",\"note_6_N_A\":\"最终笔记1-A\",\"note_6_N_B\":\"最终笔记1-B\",\"note_6_N_C\":\"最终笔记1-C\",\"note_7_N_A\":\"领主报告1-A\",\"note_7_N_B\":\"领主报告1-B\",\"note_7_N_C\":\"领主报告1-C\",\"note_0_H_A\":\"漫游日记3-A\",\"note_0_H_B\":\"漫游日记3-B\",\"note_0_H_C\":\"漫游日记3-C\",\"note_1_H_A\":\"盗贼笔记3-A\",\"note_1_H_B\":\"盗贼笔记3-B\",\"note_1_H_C\":\"盗贼笔记3-C\",\"note_2_H_A\":\"星盟资料3-A\",\"note_2_H_B\":\"星盟资料3-B\",\"note_2_H_C\":\"星盟资料3-C\",\"note_3_H_A\":\"残缺资料2-A\",\"note_3_H_B\":\"残缺资料2-B\",\"note_3_H_C\":\"残缺资料2-C\",\"note_4_H_A\":\"芯片3-A\",\"note_4_H_B\":\"芯片3-B\",\"note_4_H_C\":\"芯片3-C\",\"note_5_H_A\":\"神秘笔记3-A\",\"note_5_H_B\":\"神秘笔记3-B\",\"note_5_H_C\":\"神秘笔记3-C\",\"note_6_H_A\":\"最终笔记1-A\",\"note_6_H_B\":\"最终笔记1-B\",\"note_6_H_C\":\"最终笔记1-C\",\"note_7_H_A\":\"领主报告1-A\",\"note_7_H_B\":\"领主报告1-B\",\"note_7_H_C\":\"领主报告1-C\",\"【失败对话】\":\"游戏失败的对话\",\"note_0_GG_A\":\"漫游冒险家\",\"note_0_GG_B\":\"漫游冒险家\",\"note_0_GG_C\":\"漫游冒险家\",\"note_1_GG_A\":\"太空盗贼\",\"note_1_GG_B\":\"太空盗贼\",\"note_1_GG_C\":\"太空盗贼\",\"note_2_GG_A\":\"星盟成员\",\"note_2_GG_B\":\"星盟成员\",\"note_2_GG_C\":\"星盟成员\",\"note_3_GG_A\":\"独行者\",\"note_3_GG_B\":\"独行者\",\"note_3_GG_C\":\"独行者\",\"note_4_GG_A\":\"机器人\",\"note_4_GG_B\":\"机器人\",\"note_4_GG_C\":\"机器人\",\"note_5_GG_A\":\"神秘人\",\"note_5_GG_B\":\"神秘人\",\"note_5_GG_C\":\"神秘人\",\"note_6_GG_A\":\"时空旅行者\",\"note_6_GG_B\":\"时空旅行者\",\"note_6_GG_C\":\"时空旅行者\",\"note_7_GG_A\":\"星际领主\",\"note_7_GG_B\":\"星际领主\",\"note_7_GG_C\":\"星际领主\",\"\":0},\"story\":{\"note_0_E_A\":\"某篇日记:感觉不够\\\\这次的旅行还差得远\\\\试着前往更遥远的星系吧\\\\看看能够发现什么东西。\",\"note_0_E_B\":\"某篇日记:初始体验了跃迁引擎的能力\\\\这次先返航吧。之后再考虑去更远的地方。\",\"note_0_E_C\":\"某篇日记:跃迁引擎好像已经修复了故障\\\\尝试去一些更远的星系怎样?\",\"note_1_E_A\":\"笔记内容:团队协作是宇宙海盗的生存准则\\\\无论做什么都不能损害同伴的利益。\",\"note_1_E_B\":\"笔记内容:以探索和发现宝藏为目标\\\\而不是抢夺他人的财宝\\\\那样太没有价值了。\",\"note_1_E_C\":\"笔记内容:金币、能源、飞机 都无法保留\\\\现在最宝贵的就是新的信息和资料\\\\也就是承载大量信息的 星系币\",\"note_2_E_A\":\"星盟资料:星际联盟，21xx年成立，目的只是收留那些遭受灾难星球的流离失所的人们。\",\"note_2_E_B\":\"星盟资料:21xx年，宇宙多处星系发生了灾难，在同一时间段被不明外星组织袭击。\",\"note_2_E_C\":\"星盟资料:星际联盟本质就是一个收容所，它是在某次巨大灾难之后建立的，现在已经成为一个中立的组织。\",\"note_3_E_A\":\"资料碎片:21xx年，我的故乡星球被毁灭了,我被迫逃离了自己的家园。\",\"note_3_E_B\":\"资料碎片:星盟拒绝了我的加入，因为已经超过了它的人员限制了。\",\"note_3_E_C\":\"资料碎片:时间机器的作用是将人的记忆作为电波传输到过去的自己身上，但是这是有风险的。\",\"note_4_E_A\":\"芯片资料:能源石，是一个奇妙的物质，大部分星球都存在，它能够提供匪夷所思的大量能量。以目前科技，并不能解析它。\",\"note_4_E_B\":\"芯片资料:3D打印技术的存在，可以让飞船的制造速度大幅提升，这是几百年前也不可能发生的事情。\",\"note_4_E_C\":\"芯片资料:否定，人工智能并没有自己的思想，机器人只是按照最初设定好的指令行动罢了。\",\"note_5_E_A\":\"神秘的笔记:这个世界有一个秘密\\\\但是在世界里的人并不知道答案\\\\他们只是按照自己理解的观念来行动。\",\"note_5_E_B\":\"神秘的笔记:所以我必须引起动乱来让人们意识到某一点\\\\这个宇宙是虚假的\\\\时空穿梭也是不可能的。\",\"note_5_E_C\":\"神秘的笔记:没有人会知道为什么\\\\我会选择这条道路\\\\是我在星盟的关键几个引擎上都装载了引爆装置。\",\"note_6_E_A\":\"最后的笔记:有一个信息非常在意\\\\这些飞船\\\\好像都是一个批次出现的。\",\"note_6_E_B\":\"最后的笔记:\",\"note_6_E_C\":\"最后的笔记:\",\"note_7_E_A\":\"报告内容:感染者会在高危险度的星球出现\\\\很多危险的敌人都出现在危险度高的星球上。\",\"note_7_E_B\":\"报告内容:有些星球上还残留着自动激光武器\\\\用来击落外来的飞船\\\\但是这些科技明显是人为的。\",\"note_7_E_C\":\"报告内容:\",\"note_0_N_A\":\"某篇日记:这是错觉吗\\\\感觉陷入了一个循环之中。虽然抵达了终点\\\\但是总感觉差了点什么。\",\"note_0_N_B\":\"某篇日记:漫无边际的宇宙\\\\是否有尽头呢?我能不能找到答案?\",\"note_0_N_C\":\"某篇日记:我所在的飞船残留的资料\\\\似乎是关于时间机器的\\\\但是我不清楚为什么我会有这份资料。\",\"note_1_N_A\":\"笔记内容:在茫茫宇宙之中真的很难找到其他的舰船。当了这么久的宇宙海盗\\\\也不明白自己所追求的东西。\",\"note_1_N_B\":\"笔记内容:宇宙海盗是从未不畏惧死亡的\\\\与其说为了宝藏和财富\\\\不如说是为了探索新的可能。海盗就得有冒险精神。\",\"note_1_N_C\":\"笔记内容:我们将探索的资料储存起来\\\\储存在星系币中\\\\这样它就有了价值。是目前人类间交换资源的重要货币。\",\"note_2_N_A\":\"星盟资料:星际联盟并没有所属的星球，它是一个独立的组织，成员都位于同一艘巨大舰船内。\",\"note_2_N_B\":\"星盟资料:星盟舰船，最初是作为漂流的收容所，能够提供给10000左右的人基本的生活保障,它拥有当时最尖端的科技。\",\"note_2_N_C\":\"星盟资料:由于星盟舰船已经超过最大环境容量，现在准入机制非常严格，只有拥有大量信息技术的人才能入住。\",\"note_3_N_A\":\"资料碎片:记忆作为电波传输，会有部分信息丢失，所以会有失忆的情况发生。\",\"note_3_N_B\":\"资料碎片:丢失的记忆电波，可能被人类接收到，但是却无法被科学仪器解析。\",\"note_3_N_C\":\"资料碎片:在人类能够脱离母星，前往太空之时。外星生物也肯定会出现。茫茫宇宙之中不可能只有地球上才有生命。\",\"note_4_N_A\":\"芯片资料:外星生物，有着我们难以想象的力量。人类需要发明武器才能战斗，而大部分外星生物本身就是兵器。\",\"note_4_N_B\":\"芯片资料:金矿，只有在地球上有价值，人类之间依旧会拿金币来交易,而外星生物大多会 用 能量作为交易货币。\",\"note_4_N_C\":\"芯片资料:星系币，是一个全新的概念，只是在人类间流行的新货币，它提倡了一种 用 信息 作为交易物的新形势。\",\"note_5_N_A\":\"神秘的笔记:我进入了星盟组织\\\\是因为我能解决他们面临的难题\\\\就是时间机器的一大难点。\",\"note_5_N_B\":\"神秘的笔记:利用某种物质\\\\我们可以让空间短时间内产生巨大的能力\\\\这能量足以扭曲一切。\",\"note_5_N_C\":\"神秘的笔记:地球\\\\因为资源过度开采和使用\\\\导致环境越来越恶劣\\\\但是这时人们已经能够低成本的前往太空了。\",\"note_6_N_A\":\"最后的笔记:无限次的重复和循环\\\\每次都只能遇见这些固定的星球\\\\这一定有什么不正常！\",\"note_6_N_B\":\"最后的笔记:在星盟分崩离析之际\\\\它将大量的信息储存在星系币中\\\\我们可以从中解析出飞船的制造方法。\",\"note_6_N_C\":\"最后的笔记:我始终没有跳脱出这个星系中\\\\我不确定\\\\因为宇宙实在太辽阔了\\\\可能会看到类似的东西。\",\"note_7_N_A\":\"报告内容:由星盟研发精英初代机配备了高等水平的AI,因为对普通人来说掌握飞船的驾驶不是那么一件容易的事情。\",\"note_7_N_B\":\"报告内容:过高水平的AI反而起了反作用\\\\在无人驾驶情况下\\\\飞船通常会无差别的进行攻击。\",\"note_7_N_C\":\"报告内容:星系联盟毁灭的原因\\\\只不过是一些人类自己的纷争罢了\\\\根本没有外星生物的攻击。\",\"note_0_H_A\":\"某篇日记:对了\\\\我想起来一些事情\\\\好像刚刚发生过一般。巨大的战舰被摧毁了\\\\我们被卷入了无尽的黑暗之中。\",\"note_0_H_B\":\"某篇日记:有一点印象了\\\\我在一个收容所内\\\\不\\\\那应该是一艘飞船。这艘船收容了大量流离失所的人。\",\"note_0_H_C\":\"某篇日记:我记起来了一些人\\\\是在星盟中的小组成员\\\\当时我们驾驶另外一艘探索船在附近星系探索\\\\但是......\",\"note_1_H_A\":\"笔记内容:团队协作是宇宙海盗的生存准则\\\\无论做什么都不能损害同伴的利益。\",\"note_1_H_B\":\"笔记内容:以探索和发现宝藏为目标\\\\而不是抢夺他人的财宝\\\\那样太没有价值了。\",\"note_1_H_C\":\"笔记内容:金币、能源、飞机 都无法保留\\\\现在最宝贵的就是新的信息和资料\\\\也就是承载大量信息的 星系币。\",\"note_2_H_A\":\"星盟资料:关于时间机器\\\\其实没有人能保证成功\\\\因为现有的理论决定了\\\\物质并不能传送到过去\\\\人们只能看到过去。\",\"note_2_H_B\":\"星盟资料:银河共和国\\\\这是星盟的最终目标\\\\但是在资源不足的情况下\\\\这点是不可能实现的\\\\光是生存下去都十分艰难。\",\"note_2_H_C\":\"星盟资料:星盟的最初目的\\\\只是给无家可归的人们提供一个居所\\\\但是同时也埋下了隐患\\\\这是没有核心管理者的问题\",\"note_3_H_A\":\"资料碎片:银河护卫号似乎没有被记载在资料中\\\\让我怀疑这艘飞船是不是人类制造的。\",\"note_3_H_B\":\"资料碎片:我们确实发现了外星生物\\\\但是外星生物并没有足够的智慧\\\\对我们来说也没有帮助。\",\"note_3_H_C\":\"资料碎片:外星猿人\\\\和地球上的人们猿类很像\\\\让我感觉到找出类人生物的希望\\\\但是事实却是残酷的。\",\"note_4_H_A\":\"芯片资料:很多星球上的飞船失控了，里面的人类可能已经死亡，只是AI在执行本能的防卫操作。\",\"note_4_H_B\":\"芯片资料:在时间机器研究出来的那个瞬间，其实没有人敢相信，也没有人敢尝试。就算能够成功，这都是令人恐惧的事情。\",\"note_4_H_C\":\"芯片资料:由于很多星球被毁灭，星盟收纳了来自各个星系的最高水平的科学家团队，这件事推进了 时间机器的发明。\",\"note_5_H_A\":\"神秘的笔记:因为我必须要阻止星盟的进一步扩张\\\\这关系到未来\\\\必须亲手把它毁灭。\",\"note_5_H_B\":\"神秘的笔记:过去的我做出了一个错误的决定\\\\那就是成立星际联盟\\\\本来满怀着希望\\\\却铸成大错。\",\"note_5_H_C\":\"神秘的笔记:但是真正对未来造成了影响\\\\却是我自己\\\\如果没有我的插手\\\\事情不会变成这样的。\",\"note_6_H_A\":\"最后的笔记:整个世界不过是一个游戏\\\\所以一切不可能的事情都会发生\\\\这样\\\\时空穿越也不难解释了。\",\"note_6_H_B\":\"最后的笔记:所以我不会死亡\\\\无论多少次也能重头开始\\\\这并不是穿越了\\\\而是整个世界都在无限循环。\",\"note_6_H_C\":\"最后的笔记:几年前\\\\在星盟中\\\\我做了一件事情\\\\想要打破循环。结果是成功了\\\\但是却导致整个星盟被毁灭。\",\"note_7_H_A\":\"报告内容:发现一部分飞船的残骸\\\\认定身份标识为20xx年成立的 \\\"星际联盟\\\"。\",\"note_7_H_B\":\"报告内容:在圈外的世界\\\\依旧是一无所知\\\\但是目前也没有敢去踏足黑暗的领域。\",\"note_7_H_C\":\"报告内容:再来一次吧\\\\尽管不知道最后的答案也无所谓。\",\"【失败对话】\":\"\",\"note_0_GG_A\":\"失败了，再接再厉吧,试着用星系币解锁更多强力飞船吧。\",\"note_0_GG_B\":\"失败了，再努力一点吧,多搜集一些强力技能可能会轻松些。\",\"note_0_GG_C\":\"别灰心，再挑战一次。尽量选择低危险度的星球比较好。\",\"note_1_GG_A\":\"运气真的很糟糕，希望下次能抢来更强的飞船。\",\"note_1_GG_B\":\"失算了，看来只能重头再来了。\",\"note_1_GG_C\":\"要是有更多金币就好了，想买到更厉害的飞船。\",\"note_2_GG_A\":\"没办法，返航吧，记得技能也要留到关键的时候使用。\",\"note_2_GG_B\":\"越到后面关卡危险度会越来越高，因此敌人会变得更强。\",\"note_2_GG_C\":\"选择合适的装备搭配很重要，它们往往会发挥出惊人的作用。\",\"note_3_GG_A\":\"可能下次多收集一点强力的装备会好些,不过没关系，还有很多次机会。\",\"note_3_GG_B\":\"失败也是宝贵的经验，吸取教训，下次再努力吧。\",\"note_3_GG_C\":\"只有少量飞机时，可以躲在敌人的死角，这样就不会被攻击到了。\",\"note_4_GG_A\":\"经过分析，这次探索失败的原因是飞船能力不足，请准备更强的飞船。\",\"note_4_GG_B\":\"经过分析，这次探索失败的原因是装备搭配太差，请合理选择装备。\",\"note_4_GG_C\":\"经过分析，这次探索失败的原因是策略不对，请躲避不必要的攻击。\",\"note_5_GG_A\":\"告诉你一个秘密，如果你越强遇到的敌人也会变得更强、数量更多。\",\"note_5_GG_B\":\"告诉你一个秘密，想要获得更多的经验值,得击败更多敌人,旅行更远的距离,获得更多能量和金钱。\",\"note_5_GG_C\":\"告诉你一个秘密，想要获得RankS 就得每项都达到最高的标准。\",\"note_6_GG_A\":\"又失败了，看来只能返回到之前的时间点了。\",\"note_6_GG_B\":\"不太想继续下去了，这样的旅行什么时候结束？\",\"note_6_GG_C\":\"还是不行，就没有一个成功的方法吗?\",\"note_7_GG_A\":\"本次探索损失惨重，请及立即返航。\",\"note_7_GG_B\":\"我需要更多的星系币资源，这样才能拥有更多的飞船科技图纸。\",\"note_7_GG_C\":\"虽然探索更危险的星球获得的回报更多，但是也要考虑自己的装备水平。\",\"\":0}},\"keys\":[\"name\",\"story\"],\"items\":[\"note_0_E_A\",\"note_0_E_B\",\"note_0_E_C\",\"note_1_E_A\",\"note_1_E_B\",\"note_1_E_C\",\"note_2_E_A\",\"note_2_E_B\",\"note_2_E_C\",\"note_3_E_A\",\"note_3_E_B\",\"note_3_E_C\",\"note_4_E_A\",\"note_4_E_B\",\"note_4_E_C\",\"note_5_E_A\",\"note_5_E_B\",\"note_5_E_C\",\"note_6_E_A\",\"note_6_E_B\",\"note_6_E_C\",\"note_7_E_A\",\"note_7_E_B\",\"note_7_E_C\",\"note_0_N_A\",\"note_0_N_B\",\"note_0_N_C\",\"note_1_N_A\",\"note_1_N_B\",\"note_1_N_C\",\"note_2_N_A\",\"note_2_N_B\",\"note_2_N_C\",\"note_3_N_A\",\"note_3_N_B\",\"note_3_N_C\",\"note_4_N_A\",\"note_4_N_B\",\"note_4_N_C\",\"note_5_N_A\",\"note_5_N_B\",\"note_5_N_C\",\"note_6_N_A\",\"note_6_N_B\",\"note_6_N_C\",\"note_7_N_A\",\"note_7_N_B\",\"note_7_N_C\",\"note_0_H_A\",\"note_0_H_B\",\"note_0_H_C\",\"note_1_H_A\",\"note_1_H_B\",\"note_1_H_C\",\"note_2_H_A\",\"note_2_H_B\",\"note_2_H_C\",\"note_3_H_A\",\"note_3_H_B\",\"note_3_H_C\",\"note_4_H_A\",\"note_4_H_B\",\"note_4_H_C\",\"note_5_H_A\",\"note_5_H_B\",\"note_5_H_C\",\"note_6_H_A\",\"note_6_H_B\",\"note_6_H_C\",\"note_7_H_A\",\"note_7_H_B\",\"note_7_H_C\",\"【失败对话】\",\"note_0_GG_A\",\"note_0_GG_B\",\"note_0_GG_C\",\"note_1_GG_A\",\"note_1_GG_B\",\"note_1_GG_C\",\"note_2_GG_A\",\"note_2_GG_B\",\"note_2_GG_C\",\"note_3_GG_A\",\"note_3_GG_B\",\"note_3_GG_C\",\"note_4_GG_A\",\"note_4_GG_B\",\"note_4_GG_C\",\"note_5_GG_A\",\"note_5_GG_B\",\"note_5_GG_C\",\"note_6_GG_A\",\"note_6_GG_B\",\"note_6_GG_C\",\"note_7_GG_A\",\"note_7_GG_B\",\"note_7_GG_C\",\"\"]}"}}